{"apiVersion":0,"version":"6cae702","data":{"type":"page","count":1,"map":"1Y6PsHlF","title":"Keur Massar","subtitle":"Senegal","url":"/visit/keur-massar/1Y6PsHlF","utcOffset":0,"content":[{"items":[{"page":{"url":"/listen/radio-keur-massar/s5rnC8Jy","type":"channel","place":{"id":"1Y6PsHlF","title":"Keur Massar"},"title":"Radio Keur Massar","secure":true,"country":{"id":"2gpH1N8w","title":"Senegal"},"stream":"senemultimedia.net"}}],"itemsType":"channel","title":"Stations in Keur Massar","type":"list"},{"itemsType":"channel","title":"Picks from the Area","type":"list","items":[{"page":{"url":"/listen/urban-dakar-97-1-fm/cHuaukxl","type":"channel","place":{"id":"2YfbAACD","title":"Dakar"},"title":"Urban Dakar 97.1FM","secure":true,"country":{"id":"2gpH1N8w","title":"Senegal"},"subtitle":"Dakar","stream":"zeno.fm"}},{"page":{"url":"/listen/ndareme-fm/qtL6uikd","type":"channel","place":{"id":"Z5JBEXO5","title":"Diourbel"},"title":"Ndiaréme FM","secure":true,"country":{"id":"2gpH1N8w","title":"Senegal"},"subtitle":"Diourbel","stream":"dribbcast.com"}},{"page":{"url":"/listen/houda-fm/C3GrOB9W","type":"channel","place":{"id":"CyyA2t8Y","title":"Guediawaye"},"title":"Houda FM","secure":true,"country":{"id":"2gpH1N8w","title":"Senegal"},"subtitle":"Guediawaye","stream":"pro-fhi.net"}},{"page":{"url":"/listen/al-fayda-fm-90-1/5M0LWIJm","type":"channel","place":{"id":"QvSFtJ51","title":"Kaolack"},"title":"Al Fayda FM 90.1","secure":true,"country":{"id":"2gpH1N8w","title":"Senegal"},"subtitle":"Kaolack","stream":"fastcast4u.com"}},{"page":{"url":"/listen/carrefour-fm-90-0/ZCm6Zi22","type":"channel","place":{"id":"xnQkXjUQ","title":"Louga"},"title":"Carrefour FM 90.0","secure":true,"country":{"id":"2gpH1N8w","title":"Senegal"},"subtitle":"Louga","stream":"zeno.fm"}}]},{"itemsType":"channel","title":"Popular in Senegal","type":"list","items":[{"page":{"url":"/listen/sudfmsenradio/Z44UlSTf","type":"channel","place":{"id":"2YfbAACD","title":"Dakar"},"title":"Sud FM 98.5","secure":true,"country":{"id":"2gpH1N8w","title":"Senegal"},"subtitle":"Dakar","stream":"zeno.fm"}},{"page":{"url":"/listen/iradio-90-3/75TXW89C","type":"channel","place":{"id":"2YfbAACD","title":"Dakar"},"title":"iRADIO FM 90.3","secure":true,"country":{"id":"2gpH1N8w","title":"Senegal"},"subtitle":"Dakar","stream":"radioking.com"}},{"page":{"url":"/listen/zik-fm-89-7/nWyjIDgi","type":"channel","place":{"id":"2YfbAACD","title":"Dakar"},"title":"Zik FM 89.7","secure":true,"country":{"id":"2gpH1N8w","title":"Senegal"},"subtitle":"Dakar","stream":"zeno.fm"}},{"page":{"url":"/listen/oustaz-alioune-sall/d6M8cDq3","type":"channel","place":{"id":"2YfbAACD","title":"Dakar"},"title":"Oustaz Alioune Sall","secure":true,"country":{"id":"2gpH1N8w","title":"Senegal"},"subtitle":"Dakar","stream":"dribbcast.com"}},{"page":{"url":"/listen/dakar-fm-94-5/4oWr9XO7","type":"channel","place":{"id":"2YfbAACD","title":"Dakar"},"title":"Dakar FM 94.5","secure":true,"country":{"id":"2gpH1N8w","title":"Senegal"},"subtitle":"Dakar","stream":"zeno.fm"}},{"rightAccessory":"chevron-right","title":"Go to Senegal","type":"more","page":{"type":"page","title":"Senegal","url":"/visit/senegal/2gpH1N8w"}}]},{"rightAccessory":"chevron-right","title":"Nearby Keur Massar","type":"list","items":[{"page":{"map":"CyyA2t8Y","url":"/visit/guediawaye/CyyA2t8Y","type":"page","count":1,"title":"Guediawaye","subtitle":"Senegal"},"title":"Guediawaye","rightDetail":"9 km"},{"page":{"map":"2YfbAACD","url":"/visit/dakar/2YfbAACD","type":"page","count":25,"title":"Dakar","subtitle":"Senegal"},"title":"Dakar","rightDetail":"19 km"},{"page":{"map":"1Jf5XECO","url":"/visit/tivaouane/1Jf5XECO","type":"page","count":1,"title":"Tivaouane","subtitle":"Senegal"},"title":"Tivaouane","rightDetail":"57 km"},{"page":{"map":"Z5JBEXO5","url":"/visit/diourbel/Z5JBEXO5","type":"page","count":1,"title":"Diourbel","subtitle":"Senegal"},"title":"Diourbel","rightDetail":"117 km"},{"page":{"map":"xnQkXjUQ","url":"/visit/louga/xnQkXjUQ","type":"page","count":3,"title":"Louga","subtitle":"Senegal"},"title":"Louga","rightDetail":"148 km"}]},{"rightAccessory":"chevron-right","title":"Cities in Senegal","type":"list","items":[{"page":{"map":"2YfbAACD","url":"/visit/dakar/2YfbAACD","type":"page","count":25,"title":"Dakar","subtitle":"Senegal"},"title":"Dakar","leftAccessory":"count","leftAccessoryCount":25},{"page":{"map":"Eq68ffWB","url":"/visit/touba/Eq68ffWB","type":"page","count":6,"title":"Touba","subtitle":"Senegal"},"title":"Touba","leftAccessory":"count","leftAccessoryCount":6},{"page":{"map":"3A9HhM1W","url":"/visit/bakel/3A9HhM1W","type":"page","count":4,"title":"Bakel","subtitle":"Senegal"},"title":"Bakel","leftAccessory":"count","leftAccessoryCount":4},{"page":{"map":"xnQkXjUQ","url":"/visit/louga/xnQkXjUQ","type":"page","count":3,"title":"Louga","subtitle":"Senegal"},"title":"Louga","leftAccessory":"count","leftAccessoryCount":3},{"page":{"map":"QvSFtJ51","url":"/visit/kaolack/QvSFtJ51","type":"page","count":2,"title":"Kaolack","subtitle":"Senegal"},"title":"Kaolack","leftAccessory":"count","leftAccessoryCount":2},{"page":{"map":"Lmsr29Ni","url":"/visit/velingara/Lmsr29Ni","type":"page","count":1,"title":"Velingara","subtitle":"Senegal"},"title":"Velingara","leftAccessory":"count","leftAccessoryCount":1},{"page":{"map":"MvslE8yu","url":"/visit/ziguinchor/MvslE8yu","type":"page","count":1,"title":"Ziguinchor","subtitle":"Senegal"},"title":"Ziguinchor","leftAccessory":"count","leftAccessoryCount":1},{"page":{"map":"MQZe7F4D","url":"/visit/tambacounda/MQZe7F4D","type":"page","count":1,"title":"Tambacounda","subtitle":"Senegal"},"title":"Tambacounda","leftAccessory":"count","leftAccessoryCount":1}]}]}}