{"apiVersion":0,"version":"6cae702","data":{"type":"page","count":1,"map":"aEJ0oBoC","title":"San Andrés","subtitle":"Colombia","url":"/visit/san-andres/aEJ0oBoC","utcOffset":-300,"content":[{"items":[{"page":{"url":"/listen/marina-stereo-san-andres/Qo3U5Q1i","type":"channel","place":{"id":"aEJ0oBoC","title":"San Andrés"},"title":"Marina Stereo San Andres","secure":true,"country":{"id":"nvbh8Pbu","title":"Colombia"},"stream":"tustreamingradios2.com"}}],"itemsType":"channel","title":"Stations in San Andrés","type":"list"},{"itemsType":"channel","title":"Picks from the Area","type":"list","items":[{"page":{"url":"/listen/djx-discomovil-radio/PsAyUOOF","type":"channel","place":{"id":"FuZ1HHeW","title":"Cartago"},"title":"DJX Discomovil Radio","secure":true,"country":{"id":"Si0B7YAF","title":"Costa Rica"},"subtitle":"Cartago","stream":"zeno.fm"}},{"page":{"url":"/listen/radio-online-batalents/B16OyrEx","type":"channel","place":{"id":"_rJFNrPz","title":"Matina"},"title":"Radio Online Batalents","secure":true,"country":{"id":"Si0B7YAF","title":"Costa Rica"},"subtitle":"Matina","stream":"zeno.fm"}},{"page":{"url":"/listen/radio-cultural-pital-88-3-fm/Px4Ltrh0","type":"channel","place":{"id":"PyBUv546","title":"Pital, San Carlos"},"title":"Radio Cultural Pital 88.3 FM","secure":true,"country":{"id":"Si0B7YAF","title":"Costa Rica"},"subtitle":"Pital, San Carlos","stream":"zeno.fm"}},{"page":{"url":"/listen/radio-casino-98-3/8Wib1bSV","type":"channel","place":{"id":"fY2VFrTO","title":"Puerto Limón"},"title":"Radio Casino 98.3","secure":true,"country":{"id":"Si0B7YAF","title":"Costa Rica"},"subtitle":"Puerto Limón","stream":"rowrigo.com"}},{"page":{"url":"/listen/reggae-mistico-radio/x8syoIbg","type":"channel","place":{"id":"3z0ylfgV","title":"San Pablo"},"title":"Reggae Místico Radio","secure":true,"country":{"id":"Si0B7YAF","title":"Costa Rica"},"subtitle":"San Pablo","stream":"zeno.fm"}}]},{"itemsType":"channel","title":"Popular in Colombia","type":"list","items":[{"page":{"url":"/listen/caracol-radio/c1h8bbQ4","type":"channel","place":{"id":"E8VuzNNU","title":"Bogotá"},"title":"Caracol Radio","secure":true,"country":{"id":"nvbh8Pbu","title":"Colombia"},"subtitle":"Bogotá","stream":"streamtheworld.com"}},{"page":{"url":"/listen/blu-radio/QLobgLBk","type":"channel","place":{"id":"E8VuzNNU","title":"Bogotá"},"title":"Blu Radio","secure":true,"country":{"id":"nvbh8Pbu","title":"Colombia"},"subtitle":"Bogotá","stream":"streamtheworld.com"}},{"page":{"url":"/listen/w-radio-fm-99-9/6IElXZhJ","type":"channel","place":{"id":"E8VuzNNU","title":"Bogotá"},"title":"W Radio FM 99.9","secure":true,"country":{"id":"nvbh8Pbu","title":"Colombia"},"subtitle":"Bogotá","stream":"streamtheworld.com"}},{"page":{"url":"/listen/olimpica-stereo/IHY2DJvK","type":"channel","place":{"id":"4bt53WGI","title":"Medellín"},"title":"Olímpica Stereo","secure":true,"country":{"id":"nvbh8Pbu","title":"Colombia"},"subtitle":"Medellín","stream":"streamtheworld.com"}},{"page":{"url":"/listen/besame-bogot/YbAYM1lB","type":"channel","place":{"id":"E8VuzNNU","title":"Bogotá"},"title":"Bésame Bogotá","secure":true,"country":{"id":"nvbh8Pbu","title":"Colombia"},"subtitle":"Bogotá","stream":"streamtheworld.com"}},{"rightAccessory":"chevron-right","title":"Go to Colombia","type":"more","page":{"type":"page","title":"Colombia","url":"/visit/colombia/nvbh8Pbu"}}]},{"rightAccessory":"chevron-right","title":"Nearby San Andrés","type":"list","items":[{"page":{"map":"NYh2ULFM","url":"/visit/bluefields/NYh2ULFM","type":"page","count":2,"title":"Bluefields","subtitle":"Colombia"},"title":"Bluefields","rightDetail":"233 km"},{"page":{"map":"fY2VFrTO","url":"/visit/puerto-limon/fY2VFrTO","type":"page","count":1,"title":"Puerto Limón","subtitle":"Colombia"},"title":"Puerto Limón","rightDetail":"323 km"},{"page":{"map":"_rJFNrPz","url":"/visit/matina/_rJFNrPz","type":"page","count":1,"title":"Matina","subtitle":"Colombia"},"title":"Matina","rightDetail":"328 km"},{"page":{"map":"hE2NqGSz","url":"/visit/turrialba/hE2NqGSz","type":"page","count":2,"title":"Turrialba","subtitle":"Colombia"},"title":"Turrialba","rightDetail":"367 km"},{"page":{"map":"PyBUv546","url":"/visit/pital-san-carlos/PyBUv546","type":"page","count":1,"title":"Pital, San Carlos","subtitle":"Colombia"},"title":"Pital, San Carlos","rightDetail":"367 km"}]},{"rightAccessory":"chevron-right","title":"Cities in Colombia","type":"list","items":[{"page":{"map":"E8VuzNNU","url":"/visit/bogota/E8VuzNNU","type":"page","count":116,"title":"Bogotá","subtitle":"Colombia"},"title":"Bogotá","leftAccessory":"count","leftAccessoryCount":116},{"page":{"map":"4bt53WGI","url":"/visit/medellin/4bt53WGI","type":"page","count":55,"title":"Medellín","subtitle":"Colombia"},"title":"Medellín","leftAccessory":"count","leftAccessoryCount":55},{"page":{"map":"4oT76Ufe","url":"/visit/cali/4oT76Ufe","type":"page","count":53,"title":"Cali","subtitle":"Colombia"},"title":"Cali","leftAccessory":"count","leftAccessoryCount":53},{"page":{"map":"kvHh2EYU","url":"/visit/barranquilla/kvHh2EYU","type":"page","count":48,"title":"Barranquilla","subtitle":"Colombia"},"title":"Barranquilla","leftAccessory":"count","leftAccessoryCount":48},{"page":{"map":"LWkqcMzu","url":"/visit/tunja/LWkqcMzu","type":"page","count":26,"title":"Tunja","subtitle":"Colombia"},"title":"Tunja","leftAccessory":"count","leftAccessoryCount":26},{"page":{"map":"qRr9wBHH","url":"/visit/manizales/qRr9wBHH","type":"page","count":24,"title":"Manizales","subtitle":"Colombia"},"title":"Manizales","leftAccessory":"count","leftAccessoryCount":24},{"page":{"map":"3vxaDEK7","url":"/visit/bucaramanga/3vxaDEK7","type":"page","count":17,"title":"Bucaramanga","subtitle":"Colombia"},"title":"Bucaramanga","leftAccessory":"count","leftAccessoryCount":17},{"page":{"map":"0EHo5AJC","url":"/visit/ibague/0EHo5AJC","type":"page","count":17,"title":"Ibagué","subtitle":"Colombia"},"title":"Ibagué","leftAccessory":"count","leftAccessoryCount":17}]}]}}