{"apiVersion":0,"version":"6cae702","data":{"type":"page","count":26,"map":"LWkqcMzu","title":"Tunja","subtitle":"Colombia","url":"/visit/tunja/LWkqcMzu","utcOffset":-300,"content":[{"itemsType":"channel","title":"Stations in Tunja","type":"list","items":[{"page":{"url":"/listen/cactus-fm-tunja/BxKG-gc3","type":"channel","place":{"id":"LWkqcMzu","title":"Tunja"},"title":"Cactus FM Tunja","secure":true,"country":{"id":"nvbh8Pbu","title":"Colombia"},"stream":"zeno.fm"}},{"page":{"url":"/listen/cooservicios-stereo/MsQRqlhG","type":"channel","place":{"id":"LWkqcMzu","title":"Tunja"},"title":"Cooservicios Stereo","secure":true,"country":{"id":"nvbh8Pbu","title":"Colombia"},"stream":"zeno.fm"}},{"page":{"url":"/listen/galileo-radio-online/KnVBTksz","type":"channel","place":{"id":"LWkqcMzu","title":"Tunja"},"title":"Galileo Radio Online","secure":true,"country":{"id":"nvbh8Pbu","title":"Colombia"},"stream":"emisorasvirtuales.com"}},{"page":{"url":"/listen/la-morenita/syfU6pBr","type":"channel","place":{"id":"LWkqcMzu","title":"Tunja"},"title":"La Morenita","secure":true,"country":{"id":"nvbh8Pbu","title":"Colombia"},"stream":"paulatina.co"}},{"page":{"url":"/listen/r2-audiovisual-radio/SLZ5QDtA","type":"channel","place":{"id":"LWkqcMzu","title":"Tunja"},"title":"R2 Audiovisual Radio","secure":true,"country":{"id":"nvbh8Pbu","title":"Colombia"},"stream":"zeno.fm"}},{"page":{"url":"/listen/techno-record-fm-tunja/NFQjnMSm","type":"channel","place":{"id":"LWkqcMzu","title":"Tunja"},"title":"Techno Record FM Tunja","secure":true,"country":{"id":"nvbh8Pbu","title":"Colombia"},"stream":"zeno.fm"}},{"page":{"type":"page","count":26,"map":"LWkqcMzu","subtitle":"All Stations","title":"Tunja","url":"/visit/tunja/LWkqcMzu/channels"},"rightAccessory":"chevron-right","title":"View all 26 stations","type":"more"}]},{"actionPage":{"type":"page","count":26,"map":"LWkqcMzu","subtitle":"Popular Stations","title":"Tunja","url":"/visit/tunja/LWkqcMzu/popular"},"actionText":"See all","items":[{"page":{"url":"/listen/caracol-tunja/j1afMO9M","type":"channel","place":{"id":"LWkqcMzu","title":"Tunja"},"title":"Caracol Tunja","secure":true,"country":{"id":"nvbh8Pbu","title":"Colombia"},"stream":"streamtheworld.com"}},{"page":{"url":"/listen/la-sonora/KI9tvUYJ","type":"channel","place":{"id":"LWkqcMzu","title":"Tunja"},"title":"La Sonora 89.1 FM","secure":true,"country":{"id":"nvbh8Pbu","title":"Colombia"},"stream":"paulatina.co"}},{"page":{"url":"/listen/positiva-tunja-101-1-fm/t6ApIV28","type":"channel","place":{"id":"LWkqcMzu","title":"Tunja"},"title":"Positiva Tunja 101.1 FM","secure":true,"country":{"id":"nvbh8Pbu","title":"Colombia"},"stream":"tupanel.info"}},{"page":{"url":"/listen/rtb-radio/4kmFmdw0","type":"channel","place":{"id":"LWkqcMzu","title":"Tunja"},"title":"Radio Tuiteros Boyacá","secure":true,"country":{"id":"nvbh8Pbu","title":"Colombia"},"stream":"zeno.fm"}},{"page":{"url":"/listen/radio-chipazaque/bdhNOWlG","type":"channel","place":{"id":"LWkqcMzu","title":"Tunja"},"title":"Radio Chipazaque","secure":true,"country":{"id":"nvbh8Pbu","title":"Colombia"},"stream":"zeno.fm"}},{"page":{"url":"/listen/libertad-radio/oCNxLNMB","type":"channel","place":{"id":"LWkqcMzu","title":"Tunja"},"title":"Libertad Radio","secure":true,"country":{"id":"nvbh8Pbu","title":"Colombia"},"stream":"emisorasvirtuales.com"}}],"itemsType":"channel","title":"Popular in Tunja","type":"list"},{"itemsType":"channel","title":"Picks from the Area","type":"list","items":[{"page":{"url":"/listen/unica-fm-radio/xOicNAec","type":"channel","place":{"id":"UwTzwIuP","title":"Siachoque"},"title":"Única FM Radio","secure":true,"country":{"id":"nvbh8Pbu","title":"Colombia"},"subtitle":"Siachoque","stream":"streaminghd.co"}},{"page":{"url":"/listen/kristal-boyac/1CLWRCjI","type":"channel","place":{"id":"FyBwG3Lq","title":"Soracá"},"title":"Cristal Boyacá FM 98.3","secure":true,"country":{"id":"nvbh8Pbu","title":"Colombia"},"subtitle":"Soracá","stream":"impactodigitalcol.com"}},{"page":{"url":"/listen/roble-stereo/WjsKcNda","type":"channel","place":{"id":"lEjxMmFJ","title":"Arcabuco"},"title":"Roble Stereo","secure":true,"country":{"id":"nvbh8Pbu","title":"Colombia"},"subtitle":"Arcabuco","stream":"tikast.com"}},{"page":{"url":"/listen/manzanar-stereo/MqP9bX0o","type":"channel","place":{"id":"g-jALj1R","title":"Nuevo Colón"},"title":"Manzanar Stereo","secure":true,"country":{"id":"nvbh8Pbu","title":"Colombia"},"subtitle":"Nuevo Colón","stream":"paulatina.co"}},{"page":{"url":"/listen/nonceta-estereo-fm-92-6/gXFhFgkT","type":"channel","place":{"id":"LRhVdi1g","title":"Jenesano"},"title":"Noncetá Estéreo FM 92.6","secure":true,"country":{"id":"nvbh8Pbu","title":"Colombia"},"subtitle":"Jenesano","stream":"paulatina.co"}}]},{"itemsType":"channel","title":"Popular in Colombia","type":"list","items":[{"page":{"url":"/listen/caracol-radio/c1h8bbQ4","type":"channel","place":{"id":"E8VuzNNU","title":"Bogotá"},"title":"Caracol Radio","secure":true,"country":{"id":"nvbh8Pbu","title":"Colombia"},"subtitle":"Bogotá","stream":"streamtheworld.com"}},{"page":{"url":"/listen/blu-radio/QLobgLBk","type":"channel","place":{"id":"E8VuzNNU","title":"Bogotá"},"title":"Blu Radio","secure":true,"country":{"id":"nvbh8Pbu","title":"Colombia"},"subtitle":"Bogotá","stream":"streamtheworld.com"}},{"page":{"url":"/listen/w-radio-fm-99-9/6IElXZhJ","type":"channel","place":{"id":"E8VuzNNU","title":"Bogotá"},"title":"W Radio FM 99.9","secure":true,"country":{"id":"nvbh8Pbu","title":"Colombia"},"subtitle":"Bogotá","stream":"streamtheworld.com"}},{"page":{"url":"/listen/olimpica-stereo/IHY2DJvK","type":"channel","place":{"id":"4bt53WGI","title":"Medellín"},"title":"Olímpica Stereo","secure":true,"country":{"id":"nvbh8Pbu","title":"Colombia"},"subtitle":"Medellín","stream":"streamtheworld.com"}},{"page":{"url":"/listen/besame-bogot/YbAYM1lB","type":"channel","place":{"id":"E8VuzNNU","title":"Bogotá"},"title":"Bésame Bogotá","secure":true,"country":{"id":"nvbh8Pbu","title":"Colombia"},"subtitle":"Bogotá","stream":"streamtheworld.com"}},{"rightAccessory":"chevron-right","title":"Go to Colombia","type":"more","page":{"type":"page","title":"Colombia","url":"/visit/colombia/nvbh8Pbu"}}]},{"rightAccessory":"chevron-right","title":"Nearby Tunja","type":"list","items":[{"page":{"map":"FyBwG3Lq","url":"/visit/soraca/FyBwG3Lq","type":"page","count":1,"title":"Soracá","subtitle":"Colombia"},"title":"Soracá","rightDetail":"6 km"},{"page":{"map":"dRYL5jLI","url":"/visit/chivata/dRYL5jLI","type":"page","count":1,"title":"Chivata","subtitle":"Colombia"},"title":"Chivata","rightDetail":"8 km"},{"page":{"map":"UwTzwIuP","url":"/visit/siachoque/UwTzwIuP","type":"page","count":1,"title":"Siachoque","subtitle":"Colombia"},"title":"Siachoque","rightDetail":"13 km"},{"page":{"map":"pavpTfk0","url":"/visit/samaca/pavpTfk0","type":"page","count":1,"title":"Samacá","subtitle":"Colombia"},"title":"Samacá","rightDetail":"15 km"},{"page":{"map":"FeIz1v4m","url":"/visit/ramiriqui/FeIz1v4m","type":"page","count":1,"title":"Ramiriquí","subtitle":"Colombia"},"title":"Ramiriquí","rightDetail":"16 km"}]},{"rightAccessory":"chevron-right","title":"Cities in Colombia","type":"list","items":[{"page":{"map":"E8VuzNNU","url":"/visit/bogota/E8VuzNNU","type":"page","count":116,"title":"Bogotá","subtitle":"Colombia"},"title":"Bogotá","leftAccessory":"count","leftAccessoryCount":116},{"page":{"map":"4bt53WGI","url":"/visit/medellin/4bt53WGI","type":"page","count":55,"title":"Medellín","subtitle":"Colombia"},"title":"Medellín","leftAccessory":"count","leftAccessoryCount":55},{"page":{"map":"4oT76Ufe","url":"/visit/cali/4oT76Ufe","type":"page","count":53,"title":"Cali","subtitle":"Colombia"},"title":"Cali","leftAccessory":"count","leftAccessoryCount":53},{"page":{"map":"kvHh2EYU","url":"/visit/barranquilla/kvHh2EYU","type":"page","count":48,"title":"Barranquilla","subtitle":"Colombia"},"title":"Barranquilla","leftAccessory":"count","leftAccessoryCount":48},{"page":{"map":"qRr9wBHH","url":"/visit/manizales/qRr9wBHH","type":"page","count":24,"title":"Manizales","subtitle":"Colombia"},"title":"Manizales","leftAccessory":"count","leftAccessoryCount":24},{"page":{"map":"3vxaDEK7","url":"/visit/bucaramanga/3vxaDEK7","type":"page","count":17,"title":"Bucaramanga","subtitle":"Colombia"},"title":"Bucaramanga","leftAccessory":"count","leftAccessoryCount":17},{"page":{"map":"0EHo5AJC","url":"/visit/ibague/0EHo5AJC","type":"page","count":17,"title":"Ibagué","subtitle":"Colombia"},"title":"Ibagué","leftAccessory":"count","leftAccessoryCount":17},{"page":{"map":"6zEdXIJs","url":"/visit/villavicencio/6zEdXIJs","type":"page","count":16,"title":"Villavicencio","subtitle":"Colombia"},"title":"Villavicencio","leftAccessory":"count","leftAccessoryCount":16}]}]}}