{"apiVersion":0,"version":"6cae702","data":{"type":"page","count":2,"map":"mQCZcCDL","title":"Túxpam de Rodríguez Cano","subtitle":"Mexico","url":"/visit/tuxpam-de-rodriguez-cano/mQCZcCDL","utcOffset":-360,"content":[{"items":[{"page":{"url":"/listen/la-poderosa-93-1-fm/7e0E5LZn","type":"channel","place":{"id":"mQCZcCDL","title":"Túxpam de Rodríguez Cano"},"title":"La Poderosa 93.1 FM","secure":true,"country":{"id":"wnXlJnnm","title":"Mexico"},"stream":"zeno.fm"}},{"page":{"url":"/listen/vida-azul-95-9-fm-xhtvr/ZVT0CsLO","type":"channel","place":{"id":"mQCZcCDL","title":"Túxpam de Rodríguez Cano"},"title":"Vida Azul 95.9 FM - XHTVR","secure":true,"country":{"id":"wnXlJnnm","title":"Mexico"},"stream":"zeno.fm"}}],"itemsType":"channel","title":"Stations in Túxpam de Rodríguez Cano","type":"list"},{"itemsType":"channel","title":"Picks from the Area","type":"list","items":[{"page":{"url":"/listen/21-radio/c7xU7zaS","type":"channel","place":{"id":"LbTrsK0N","title":"Naranjos"},"title":"21Radio","secure":true,"country":{"id":"wnXlJnnm","title":"Mexico"},"subtitle":"Naranjos","stream":"reynosonika.online"}},{"page":{"url":"/listen/extasis-digital-105-9-fm-xhcov/i-bpmga7","type":"channel","place":{"id":"3Bm8TXPt","title":"Poza Rica de Hidalgo"},"title":"Extasis Digital 105.9 FM - XHCOV","secure":true,"country":{"id":"wnXlJnnm","title":"Mexico"},"subtitle":"Poza Rica de Hidalgo","stream":"zeno.fm"}},{"page":{"url":"/listen/soy-fm-93-9/wCmpDrZT","type":"channel","place":{"id":"2iythsSg","title":"Túxpan"},"title":"Soy FM 93.9","secure":true,"country":{"id":"wnXlJnnm","title":"Mexico"},"subtitle":"Túxpan","stream":"streann.com"}},{"page":{"url":"/listen/ultra-91-7-fm/cxaOiiyX","type":"channel","place":{"id":"E2nENEJU","title":"Huauchinango"},"title":"Ultra 91.7 FM","secure":true,"country":{"id":"wnXlJnnm","title":"Mexico"},"subtitle":"Huauchinango","stream":"duckdns.org"}},{"page":{"url":"/listen/radio-jerusalen-101-5-fm/9c7HIXQJ","type":"channel","place":{"id":"pv7yD91g","title":"Huejutla de Reyes"},"title":"Radio Jerusalen 101.5 FM","secure":true,"country":{"id":"wnXlJnnm","title":"Mexico"},"subtitle":"Huejutla de Reyes","stream":"wanderingsheep.net"}}]},{"itemsType":"channel","title":"Popular in Mexico","type":"list","items":[{"page":{"url":"/listen/universal-88-1/HCxAbj-9","type":"channel","place":{"id":"mFxWfHUs","title":"Mexico City"},"title":"Universal 88.1","secure":true,"country":{"id":"wnXlJnnm","title":"Mexico"},"subtitle":"Mexico City","stream":"streamtheworld.com"}},{"page":{"url":"/listen/radio-centro-el-fonografo-am-690/xNZ4GfTN","type":"channel","place":{"id":"mFxWfHUs","title":"Mexico City"},"title":"Radio Centro El Fonografo AM 690","secure":true,"country":{"id":"wnXlJnnm","title":"Mexico"},"subtitle":"Mexico City","stream":"streamtheworld.com"}},{"page":{"url":"/listen/cafe-romantico-radio/PUD7NslA","type":"channel","place":{"id":"bLh0ZBR6","title":"Monterrey"},"title":"Cafe Romantico Radio","secure":true,"country":{"id":"wnXlJnnm","title":"Mexico"},"subtitle":"Monterrey","stream":"retrolandigital.com"}},{"page":{"url":"/listen/w-radio-fm-96-9/o3jhb5Bg","type":"channel","place":{"id":"mFxWfHUs","title":"Mexico City"},"title":"W Radio FM 96.9","secure":true,"country":{"id":"wnXlJnnm","title":"Mexico"},"subtitle":"Mexico City","stream":"streamtheworld.com"}},{"page":{"url":"/listen/cumbias-inmortales-radio/en6nxtHN","type":"channel","place":{"id":"bLh0ZBR6","title":"Monterrey"},"title":"Cumbias Inmortales Radio","secure":true,"country":{"id":"wnXlJnnm","title":"Mexico"},"subtitle":"Monterrey","stream":"retrolandigital.com"}},{"rightAccessory":"chevron-right","title":"Go to Mexico","type":"more","page":{"type":"page","title":"Mexico","url":"/visit/mexico/wnXlJnnm"}}]},{"rightAccessory":"chevron-right","title":"Nearby Túxpam de Rodríguez Cano","type":"list","items":[{"page":{"map":"2iythsSg","url":"/visit/tuxpan/2iythsSg","type":"page","count":2,"title":"Túxpan","subtitle":"Mexico"},"title":"Túxpan","rightDetail":"0 km"},{"page":{"map":"3Bm8TXPt","url":"/visit/poza-rica-de-hidalgo/3Bm8TXPt","type":"page","count":1,"title":"Poza Rica de Hidalgo","subtitle":"Mexico"},"title":"Poza Rica de Hidalgo","rightDetail":"48 km"},{"page":{"map":"LbTrsK0N","url":"/visit/naranjos/LbTrsK0N","type":"page","count":2,"title":"Naranjos","subtitle":"Mexico"},"title":"Naranjos","rightDetail":"52 km"},{"page":{"map":"WPoXkiLa","url":"/visit/papantla/WPoXkiLa","type":"page","count":2,"title":"Papantla","subtitle":"Mexico"},"title":"Papantla","rightDetail":"56 km"},{"page":{"map":"Hh1ryCdM","url":"/visit/tamalin/Hh1ryCdM","type":"page","count":1,"title":"Tamalín","subtitle":"Mexico"},"title":"Tamalín","rightDetail":"60 km"}]},{"rightAccessory":"chevron-right","title":"Cities in Mexico","type":"list","items":[{"page":{"map":"mFxWfHUs","url":"/visit/mexico-city/mFxWfHUs","type":"page","count":99,"title":"Mexico City","subtitle":"Mexico"},"title":"Mexico City","leftAccessory":"count","leftAccessoryCount":99},{"page":{"map":"ItDApT9y","url":"/visit/guadalajara/ItDApT9y","type":"page","count":42,"title":"Guadalajara","subtitle":"Mexico"},"title":"Guadalajara","leftAccessory":"count","leftAccessoryCount":42},{"page":{"map":"bLh0ZBR6","url":"/visit/monterrey/bLh0ZBR6","type":"page","count":40,"title":"Monterrey","subtitle":"Mexico"},"title":"Monterrey","leftAccessory":"count","leftAccessoryCount":40},{"page":{"map":"TMWcJ9Pj","url":"/visit/puebla/TMWcJ9Pj","type":"page","count":21,"title":"Puebla","subtitle":"Mexico"},"title":"Puebla","leftAccessory":"count","leftAccessoryCount":21},{"page":{"map":"GiGeErfR","url":"/visit/merida/GiGeErfR","type":"page","count":21,"title":"Merida","subtitle":"Mexico"},"title":"Merida","leftAccessory":"count","leftAccessoryCount":21},{"page":{"map":"rjCmmI9N","url":"/visit/heroica-veracruz/rjCmmI9N","type":"page","count":17,"title":"Heroica Veracruz","subtitle":"Mexico"},"title":"Heroica Veracruz","leftAccessory":"count","leftAccessoryCount":17},{"page":{"map":"YoEBcmr8","url":"/visit/san-luis-potosi/YoEBcmr8","type":"page","count":17,"title":"San Luis Potosi","subtitle":"Mexico"},"title":"San Luis Potosi","leftAccessory":"count","leftAccessoryCount":17},{"page":{"map":"EQ1OlqGN","url":"/visit/cuernavaca/EQ1OlqGN","type":"page","count":17,"title":"Cuernavaca","subtitle":"Mexico"},"title":"Cuernavaca","leftAccessory":"count","leftAccessoryCount":17}]}]}}