{"apiVersion":0,"version":"6cae702","data":{"type":"page","count":2,"map":"qmRvLp9I","title":"Lucena","subtitle":"Spain","url":"/visit/lucena/qmRvLp9I","utcOffset":120,"content":[{"items":[{"page":{"url":"/listen/ser-lucena-95-7-fm/HicI8b0P","type":"channel","place":{"id":"qmRvLp9I","title":"Lucena"},"title":"SER Lucena 95.7 FM","secure":true,"country":{"id":"V9cvEXA9","title":"Spain"},"stream":"streamtheworld.com"}},{"page":{"url":"/listen/dial-lucena/WRb97tvc","type":"channel","place":{"id":"qmRvLp9I","title":"Lucena"},"title":"Dial Lucena","secure":true,"country":{"id":"V9cvEXA9","title":"Spain"},"stream":"streamtheworld.com"}}],"itemsType":"channel","title":"Stations in Lucena","type":"list"},{"itemsType":"channel","title":"Picks from the Area","type":"list","items":[{"page":{"url":"/listen/onda-mencia-radio/ddrSEKy2","type":"channel","place":{"id":"DINDDIrP","title":"Doña Mencía"},"title":"Onda Mencía Radio","secure":true,"country":{"id":"V9cvEXA9","title":"Spain"},"subtitle":"Doña Mencía","stream":"elitecomunicacion.es"}},{"page":{"url":"/listen/los-40-100-4-fm/MO9Gkwj7","type":"channel","place":{"id":"t6eAw8Zw","title":"Antequera"},"title":"LOS40 100.4 FM","secure":true,"country":{"id":"V9cvEXA9","title":"Spain"},"subtitle":"Antequera","stream":"streamtheworld.com"}},{"page":{"url":"/listen/onda-marina/68oISE69","type":"channel","place":{"id":"16vxPGCG","title":"Fernán-Núñez"},"title":"Onda Marina","secure":true,"country":{"id":"V9cvEXA9","title":"Spain"},"subtitle":"Fernán-Núñez","stream":"dns-lcinternet.com"}},{"page":{"url":"/listen/onda-pasion-107-7-fm/D9OZe7Gf","type":"channel","place":{"id":"qFnr2LjA","title":"La Rambla"},"title":"Onda Pasión 107.7 FM","secure":true,"country":{"id":"V9cvEXA9","title":"Spain"},"subtitle":"La Rambla","stream":"elitecomunicacion.es"}},{"page":{"url":"/listen/radio-rute-f-m/mvdYx355","type":"channel","place":{"id":"5Tt2c9xe","title":"Rute"},"title":"Radio Rute FM 107.8","secure":true,"country":{"id":"V9cvEXA9","title":"Spain"},"subtitle":"Rute","stream":"elitecomunicacion.es"}}]},{"itemsType":"channel","title":"Popular in Spain","type":"list","items":[{"page":{"url":"/listen/cope-madrid/RO3xvxeU","type":"channel","place":{"id":"hFG1a7Dk","title":"Madrid"},"title":"COPE Madrid","secure":true,"country":{"id":"V9cvEXA9","title":"Spain"},"subtitle":"Madrid","stream":"flumotion.com"}},{"page":{"url":"/listen/cadenaser/piGwX76D","type":"channel","place":{"id":"hFG1a7Dk","title":"Madrid"},"title":"Cadena Ser","secure":true,"country":{"id":"V9cvEXA9","title":"Spain"},"subtitle":"Madrid","stream":"streamtheworld.com"}},{"page":{"url":"/listen/esradio/HGMbdCXa","type":"channel","place":{"id":"hFG1a7Dk","title":"Madrid"},"title":"esRadio","secure":true,"country":{"id":"V9cvEXA9","title":"Spain"},"subtitle":"Madrid","stream":"flumotion.com"}},{"page":{"url":"/listen/rock-fm/rjv2cBe2","type":"channel","place":{"id":"hFG1a7Dk","title":"Madrid"},"title":"Rock FM","secure":true,"country":{"id":"V9cvEXA9","title":"Spain"},"subtitle":"Madrid","stream":"flumotion.com"}},{"page":{"url":"/listen/cadena-100/D1UBtS5T","type":"channel","place":{"id":"hFG1a7Dk","title":"Madrid"},"title":"Cadena 100","secure":true,"country":{"id":"V9cvEXA9","title":"Spain"},"subtitle":"Madrid","stream":"flumotion.com"}},{"rightAccessory":"chevron-right","title":"Go to Spain","type":"more","page":{"type":"page","title":"Spain","url":"/visit/spain/V9cvEXA9"}}]},{"rightAccessory":"chevron-right","title":"Nearby Lucena","type":"list","items":[{"page":{"map":"5Tt2c9xe","url":"/visit/rute/5Tt2c9xe","type":"page","count":1,"title":"Rute","subtitle":"Spain"},"title":"Rute","rightDetail":"12 km"},{"page":{"map":"DINDDIrP","url":"/visit/dona-mencia/DINDDIrP","type":"page","count":1,"title":"Doña Mencía","subtitle":"Spain"},"title":"Doña Mencía","rightDetail":"20 km"},{"page":{"map":"aDUlQTwv","url":"/visit/puente-genil/aDUlQTwv","type":"page","count":2,"title":"Puente Genil","subtitle":"Spain"},"title":"Puente Genil","rightDetail":"24 km"},{"page":{"map":"pWdXJL--","url":"/visit/montalban-de-cordoba/pWdXJL--","type":"page","count":1,"title":"Montalbán de Córdoba","subtitle":"Spain"},"title":"Montalbán de Córdoba","rightDetail":"29 km"},{"page":{"map":"qFnr2LjA","url":"/visit/la-rambla/qFnr2LjA","type":"page","count":1,"title":"La Rambla","subtitle":"Spain"},"title":"La Rambla","rightDetail":"30 km"}]},{"rightAccessory":"chevron-right","title":"Cities in Spain","type":"list","items":[{"page":{"map":"hFG1a7Dk","url":"/visit/madrid/hFG1a7Dk","type":"page","count":104,"title":"Madrid","subtitle":"Spain"},"title":"Madrid","leftAccessory":"count","leftAccessoryCount":104},{"page":{"map":"DySRBHdL","url":"/visit/barcelona/DySRBHdL","type":"page","count":44,"title":"Barcelona","subtitle":"Spain"},"title":"Barcelona","leftAccessory":"count","leftAccessoryCount":44},{"page":{"map":"BQp7EEgW","url":"/visit/palma/BQp7EEgW","type":"page","count":35,"title":"Palma de Mallorca","subtitle":"Spain"},"title":"Palma de Mallorca","leftAccessory":"count","leftAccessoryCount":35},{"page":{"map":"xdFoGP7o","url":"/visit/malaga/xdFoGP7o","type":"page","count":33,"title":"Málaga","subtitle":"Spain"},"title":"Málaga","leftAccessory":"count","leftAccessoryCount":33},{"page":{"map":"yww6IvMD","url":"/visit/valencia/yww6IvMD","type":"page","count":25,"title":"Valencia","subtitle":"Spain"},"title":"Valencia","leftAccessory":"count","leftAccessoryCount":25},{"page":{"map":"6DT6YRBu","url":"/visit/seville/6DT6YRBu","type":"page","count":24,"title":"Seville","subtitle":"Spain"},"title":"Seville","leftAccessory":"count","leftAccessoryCount":24},{"page":{"map":"UpWDKzmZ","url":"/visit/ibiza/UpWDKzmZ","type":"page","count":22,"title":"Ibiza","subtitle":"Spain"},"title":"Ibiza","leftAccessory":"count","leftAccessoryCount":22},{"page":{"map":"BAybPmHT","url":"/visit/santa-cruz-de-tenerife/BAybPmHT","type":"page","count":21,"title":"Santa Cruz de Tenerife","subtitle":"Spain"},"title":"Santa Cruz de Tenerife","leftAccessory":"count","leftAccessoryCount":21}]}]}}