{"apiVersion":0,"version":"6cae702","data":{"type":"page","count":1,"map":"v3_dmAq4","title":"Lelydorp","subtitle":"Suriname","url":"/visit/lelydorp/v3_dmAq4","utcOffset":-180,"content":[{"items":[{"page":{"url":"/listen/neutralradio/0cF8C1sM","type":"channel","place":{"id":"v3_dmAq4","title":"Lelydorp"},"title":"Neutralradio","secure":true,"country":{"id":"1wEjneGQ","title":"Suriname"},"stream":"torontocast.com"}}],"itemsType":"channel","title":"Stations in Lelydorp","type":"list"},{"itemsType":"channel","title":"Picks from the Area","type":"list","items":[{"page":{"url":"/listen/monte-roraima-fm-107-9/uSYD4hMR","type":"channel","place":{"id":"ARhMAFGl","title":"Boa Vista RR"},"title":"Monte Roraima FM 107.9","secure":true,"country":{"id":"Fx52MfoZ","title":"Brazil"},"subtitle":"Boa Vista RR","stream":"com.br"}},{"page":{"url":"/listen/radio-play-ap/MOJGzPTp","type":"channel","place":{"id":"KodWBKgM","title":"Macapá AP"},"title":"Rádio Play AP","secure":true,"country":{"id":"Fx52MfoZ","title":"Brazil"},"subtitle":"Macapá AP","stream":"com.br"}},{"page":{"url":"/listen/jovem-santana-fm-92-3/HooY3YXP","type":"channel","place":{"id":"QSW0NTX6","title":"Santana AP"},"title":"Jovem Santana FM 92.3","secure":true,"country":{"id":"Fx52MfoZ","title":"Brazil"},"subtitle":"Santana AP","stream":"com.br"}},{"page":{"url":"/listen/chwitiweb/09aAemz7","type":"channel","place":{"id":"ufWZ1Cpb","title":"Cayenne"},"title":"Chwitiweb","secure":true,"country":{"id":"KQYBUDIF","title":"French Guiana"},"subtitle":"Cayenne","stream":"radioking.com"}},{"page":{"url":"/listen/rfo-guyane-1ere/TOCAGU9z","type":"channel","place":{"id":"zDz5yObV","title":"Remire-Montjoly"},"title":"RFO Guyane 1ère FM 92.0","secure":true,"country":{"id":"KQYBUDIF","title":"French Guiana"},"subtitle":"Remire-Montjoly","stream":"infomaniak.ch"}}]},{"itemsType":"channel","title":"Popular in Suriname","type":"list","items":[{"page":{"url":"/listen/radio-10/QJ2fWCHl","type":"channel","place":{"id":"5poR6yYe","title":"Paramaribo"},"title":"Radio 10 Magic FM 88.1","secure":true,"country":{"id":"1wEjneGQ","title":"Suriname"},"subtitle":"Paramaribo","stream":"radio.co"}},{"page":{"url":"/listen/radio-abc-fm-101-7/EH0jCFf6","type":"channel","place":{"id":"5poR6yYe","title":"Paramaribo"},"title":"Radio ABC FM 101.7","secure":true,"country":{"id":"1wEjneGQ","title":"Suriname"},"subtitle":"Paramaribo","stream":"surilive.com"}},{"page":{"url":"/listen/radio-apintie-suriname-fm-97-1/TqEoipFP","type":"channel","place":{"id":"5poR6yYe","title":"Paramaribo"},"title":"Radio Apintie FM 97.1","secure":true,"country":{"id":"1wEjneGQ","title":"Suriname"},"subtitle":"Paramaribo","stream":"surilive.com"}},{"page":{"url":"/listen/radio-srs-fm-96-3/PlXWaEnV","type":"channel","place":{"id":"5poR6yYe","title":"Paramaribo"},"title":"Radio SRS FM 96.3","secure":true,"country":{"id":"1wEjneGQ","title":"Suriname"},"subtitle":"Paramaribo","stream":"surilive.com"}},{"page":{"url":"/listen/radio-9-suriname/We1DXBoV","type":"channel","place":{"id":"5poR6yYe","title":"Paramaribo"},"title":"Radio 9 Suriname","secure":true,"country":{"id":"1wEjneGQ","title":"Suriname"},"subtitle":"Paramaribo","stream":"suricloud.com"}},{"rightAccessory":"chevron-right","title":"Go to Suriname","type":"more","page":{"type":"page","title":"Suriname","url":"/visit/suriname/1wEjneGQ"}}]},{"rightAccessory":"chevron-right","title":"Nearby Lelydorp","type":"list","items":[{"page":{"map":"5poR6yYe","url":"/visit/paramaribo/5poR6yYe","type":"page","count":17,"title":"Paramaribo","subtitle":"Suriname"},"title":"Paramaribo","rightDetail":"16 km"},{"page":{"map":"ufWZ1Cpb","url":"/visit/cayenne/ufWZ1Cpb","type":"page","count":3,"title":"Cayenne","subtitle":"Suriname"},"title":"Cayenne","rightDetail":"334 km"},{"page":{"map":"zDz5yObV","url":"/visit/remire-montjoly/zDz5yObV","type":"page","count":1,"title":"Remire-Montjoly","subtitle":"Suriname"},"title":"Remire-Montjoly","rightDetail":"338 km"},{"page":{"map":"2UKb8PUW","url":"/visit/linden/2UKb8PUW","type":"page","count":1,"title":"Linden","subtitle":"Suriname"},"title":"Linden","rightDetail":"344 km"},{"page":{"map":"2hSBzjBz","url":"/visit/georgetown/2hSBzjBz","type":"page","count":9,"title":"Georgetown","subtitle":"Suriname"},"title":"Georgetown","rightDetail":"347 km"}]},{"rightAccessory":"chevron-right","title":"Cities in Suriname","type":"list","items":[{"page":{"map":"5poR6yYe","url":"/visit/paramaribo/5poR6yYe","type":"page","count":17,"title":"Paramaribo","subtitle":"Suriname"},"title":"Paramaribo","leftAccessory":"count","leftAccessoryCount":17}]}]}}