{"apiVersion":0,"version":"6cae702","data":{"type":"page","count":1,"map":"3BXxAVLo","title":"San Martín","subtitle":"Colombia","url":"/visit/san-martin/3BXxAVLo","utcOffset":-300,"content":[{"items":[{"page":{"url":"/listen/san-martin-radio/6NaWEub4","type":"channel","place":{"id":"3BXxAVLo","title":"San Martín"},"title":"San Martín Radio","secure":true,"country":{"id":"nvbh8Pbu","title":"Colombia"},"stream":"paulatina.co"}}],"itemsType":"channel","title":"Stations in San Martín","type":"list"},{"itemsType":"channel","title":"Picks from the Area","type":"list","items":[{"page":{"url":"/listen/colvalencia-radio-93-7-fm/bcR5oBwy","type":"channel","place":{"id":"qyu50wAM","title":"Aguachica"},"title":"Colvalencia Radio 93.7 FM","secure":true,"country":{"id":"nvbh8Pbu","title":"Colombia"},"subtitle":"Aguachica","stream":"streaminghd.co"}},{"page":{"url":"/listen/ritmo-stereo-fm-99-7/n3_iL2M7","type":"channel","place":{"id":"N3Yzm96Z","title":"Duranía"},"title":"Ritmo Stereo FM 99.7","secure":true,"country":{"id":"nvbh8Pbu","title":"Colombia"},"subtitle":"Duranía","stream":"zeno.fm"}},{"page":{"url":"/listen/vst-radio/n-mHsXgw","type":"channel","place":{"id":"e9RhWmee","title":"Higueron"},"title":"VST Radio FM 98.3","secure":true,"country":{"id":"nvbh8Pbu","title":"Colombia"},"subtitle":"Higueron","stream":"virtualtronics.com"}},{"page":{"url":"/listen/ocana-digital-radio/yVqql4jL","type":"channel","place":{"id":"oVzDPBI8","title":"Ocaña"},"title":"Ocaña Digital Radio","secure":true,"country":{"id":"nvbh8Pbu","title":"Colombia"},"subtitle":"Ocaña","stream":"intermediacolombia.com"}},{"page":{"url":"/listen/radio-107-3-teurama-estereo-fm/P-8fSv_x","type":"channel","place":{"id":"1_VI2FDW","title":"Teorama"},"title":"Teurama Estéreo FM 107.3","secure":true,"country":{"id":"nvbh8Pbu","title":"Colombia"},"subtitle":"Teorama","stream":"virtualtronics.com"}}]},{"itemsType":"channel","title":"Popular in Colombia","type":"list","items":[{"page":{"url":"/listen/caracol-radio/c1h8bbQ4","type":"channel","place":{"id":"E8VuzNNU","title":"Bogotá"},"title":"Caracol Radio","secure":true,"country":{"id":"nvbh8Pbu","title":"Colombia"},"subtitle":"Bogotá","stream":"streamtheworld.com"}},{"page":{"url":"/listen/blu-radio/QLobgLBk","type":"channel","place":{"id":"E8VuzNNU","title":"Bogotá"},"title":"Blu Radio","secure":true,"country":{"id":"nvbh8Pbu","title":"Colombia"},"subtitle":"Bogotá","stream":"streamtheworld.com"}},{"page":{"url":"/listen/w-radio-fm-99-9/6IElXZhJ","type":"channel","place":{"id":"E8VuzNNU","title":"Bogotá"},"title":"W Radio FM 99.9","secure":true,"country":{"id":"nvbh8Pbu","title":"Colombia"},"subtitle":"Bogotá","stream":"streamtheworld.com"}},{"page":{"url":"/listen/olimpica-stereo/IHY2DJvK","type":"channel","place":{"id":"4bt53WGI","title":"Medellín"},"title":"Olímpica Stereo","secure":true,"country":{"id":"nvbh8Pbu","title":"Colombia"},"subtitle":"Medellín","stream":"streamtheworld.com"}},{"page":{"url":"/listen/besame-bogot/YbAYM1lB","type":"channel","place":{"id":"E8VuzNNU","title":"Bogotá"},"title":"Bésame Bogotá","secure":true,"country":{"id":"nvbh8Pbu","title":"Colombia"},"subtitle":"Bogotá","stream":"streamtheworld.com"}},{"rightAccessory":"chevron-right","title":"Go to Colombia","type":"more","page":{"type":"page","title":"Colombia","url":"/visit/colombia/nvbh8Pbu"}}]},{"rightAccessory":"chevron-right","title":"Nearby San Martín","type":"list","items":[{"page":{"map":"vtyaC1pz","url":"/visit/san-alberto/vtyaC1pz","type":"page","count":1,"title":"San Alberto","subtitle":"Colombia"},"title":"San Alberto","rightDetail":"30 km"},{"page":{"map":"oVzDPBI8","url":"/visit/ocana/oVzDPBI8","type":"page","count":4,"title":"Ocaña","subtitle":"Colombia"},"title":"Ocaña","rightDetail":"33 km"},{"page":{"map":"e9RhWmee","url":"/visit/higueron/e9RhWmee","type":"page","count":1,"title":"Higueron","subtitle":"Colombia"},"title":"Higueron","rightDetail":"35 km"},{"page":{"map":"qyu50wAM","url":"/visit/aguachica/qyu50wAM","type":"page","count":3,"title":"Aguachica","subtitle":"Colombia"},"title":"Aguachica","rightDetail":"36 km"},{"page":{"map":"1_VI2FDW","url":"/visit/teorama/1_VI2FDW","type":"page","count":1,"title":"Teorama","subtitle":"Colombia"},"title":"Teorama","rightDetail":"54 km"}]},{"rightAccessory":"chevron-right","title":"Cities in Colombia","type":"list","items":[{"page":{"map":"E8VuzNNU","url":"/visit/bogota/E8VuzNNU","type":"page","count":116,"title":"Bogotá","subtitle":"Colombia"},"title":"Bogotá","leftAccessory":"count","leftAccessoryCount":116},{"page":{"map":"4bt53WGI","url":"/visit/medellin/4bt53WGI","type":"page","count":55,"title":"Medellín","subtitle":"Colombia"},"title":"Medellín","leftAccessory":"count","leftAccessoryCount":55},{"page":{"map":"4oT76Ufe","url":"/visit/cali/4oT76Ufe","type":"page","count":53,"title":"Cali","subtitle":"Colombia"},"title":"Cali","leftAccessory":"count","leftAccessoryCount":53},{"page":{"map":"kvHh2EYU","url":"/visit/barranquilla/kvHh2EYU","type":"page","count":48,"title":"Barranquilla","subtitle":"Colombia"},"title":"Barranquilla","leftAccessory":"count","leftAccessoryCount":48},{"page":{"map":"LWkqcMzu","url":"/visit/tunja/LWkqcMzu","type":"page","count":26,"title":"Tunja","subtitle":"Colombia"},"title":"Tunja","leftAccessory":"count","leftAccessoryCount":26},{"page":{"map":"qRr9wBHH","url":"/visit/manizales/qRr9wBHH","type":"page","count":24,"title":"Manizales","subtitle":"Colombia"},"title":"Manizales","leftAccessory":"count","leftAccessoryCount":24},{"page":{"map":"3vxaDEK7","url":"/visit/bucaramanga/3vxaDEK7","type":"page","count":17,"title":"Bucaramanga","subtitle":"Colombia"},"title":"Bucaramanga","leftAccessory":"count","leftAccessoryCount":17},{"page":{"map":"0EHo5AJC","url":"/visit/ibague/0EHo5AJC","type":"page","count":17,"title":"Ibagué","subtitle":"Colombia"},"title":"Ibagué","leftAccessory":"count","leftAccessoryCount":17}]}]}}