{"apiVersion":0,"version":"6cae702","data":{"type":"page","count":1,"map":"5JkEvm8t","title":"Maldá","subtitle":"India","url":"/visit/malda/5JkEvm8t","utcOffset":330,"content":[{"items":[{"page":{"url":"/listen/radio-malda-90-4-fm/s63fh4h0","type":"channel","place":{"id":"5JkEvm8t","title":"Maldá"},"title":"Radio Malda 90.4 FM","secure":true,"country":{"id":"BOs9FZg4","title":"India"},"stream":"zeno.fm"}}],"itemsType":"channel","title":"Stations in Maldá","type":"list"},{"itemsType":"channel","title":"Picks from the Area","type":"list","items":[{"page":{"url":"/listen/radio-mahananda-98-8-fm/kiblpBAm","type":"channel","place":{"id":"_52aFIUv","title":"Chapai Nawabganj"},"title":"Radio Mahananda 98.8 FM","secure":true,"country":{"id":"btQcSfRc","title":"Bangladesh"},"subtitle":"Chapai Nawabganj","stream":"radiomahananda.fm"}},{"page":{"url":"/listen/radio-padma-99-2/rZztipXo","type":"channel","place":{"id":"f09uPaXs","title":"Rajshahi"},"title":"Radio Padma 99.2","secure":true,"country":{"id":"btQcSfRc","title":"Bangladesh"},"subtitle":"Rajshahi","stream":"radioca.st"}},{"page":{"url":"/listen/radio-active-fm-90-4/D3zo2tNf","type":"channel","place":{"id":"wtU7bpKo","title":"Bhagalpur"},"title":"Radio Active FM 90.4","secure":true,"country":{"id":"BOs9FZg4","title":"India"},"subtitle":"Bhagalpur","stream":"zeno.fm"}},{"page":{"url":"/listen/edudew-radio/RjSz9Bjj","type":"channel","place":{"id":"sh_fnykm","title":"Deoghar"},"title":"Edudew Radio","secure":true,"country":{"id":"BOs9FZg4","title":"India"},"subtitle":"Deoghar","stream":"edudew.com"}},{"page":{"url":"/listen/raha-fm/Y2Xmpv9m","type":"channel","place":{"id":"MdUqp1Fl","title":"Dumka"},"title":"Raha FM","secure":true,"country":{"id":"BOs9FZg4","title":"India"},"subtitle":"Dumka","stream":"zeno.fm"}}]},{"itemsType":"channel","title":"Popular in India","type":"list","items":[{"page":{"url":"/listen/vaigai-fm/8yCs65rl","type":"channel","place":{"id":"jTflzNk8","title":"Rajapalayam"},"title":"Vaigai FM","secure":true,"country":{"id":"BOs9FZg4","title":"India"},"subtitle":"Rajapalayam","stream":"my-control-panel.com"}},{"page":{"url":"/listen/kodaicity-fm/woMEg1wo","type":"channel","place":{"id":"WA6TK5oG","title":"Kodaikanal"},"title":"Kodaicity FM கோடைசிட்டி  இணைய வானொலி","secure":true,"country":{"id":"BOs9FZg4","title":"India"},"subtitle":"Kodaikanal","stream":"openstream.co"}},{"page":{"url":"/listen/kodairagam-radio/gxssf1Io","type":"channel","place":{"id":"WA6TK5oG","title":"Kodaikanal"},"title":"Kodairagam Radio","secure":true,"country":{"id":"BOs9FZg4","title":"India"},"subtitle":"Kodaikanal","stream":"my-control-panel.com"}},{"page":{"url":"/listen/dindigul-radio/qwY6vAK7","type":"channel","place":{"id":"lhQwDfRn","title":"Dindigul"},"title":"Dindigul Radio","secure":true,"country":{"id":"BOs9FZg4","title":"India"},"subtitle":"Dindigul","stream":"sscast2u.in"}},{"page":{"url":"/listen/vani-online-radio/Px2h9dgq","type":"channel","place":{"id":"HliOlB8P","title":"Kovilpatti"},"title":"Vani Online Radio","secure":true,"country":{"id":"BOs9FZg4","title":"India"},"subtitle":"Kovilpatti","stream":"sscast2u.in"}},{"rightAccessory":"chevron-right","title":"Go to India","type":"more","page":{"type":"page","title":"India","url":"/visit/india/BOs9FZg4"}}]},{"rightAccessory":"chevron-right","title":"Nearby Maldá","type":"list","items":[{"page":{"map":"_52aFIUv","url":"/visit/chapai-nawabganj/_52aFIUv","type":"page","count":1,"title":"Chapai Nawabganj","subtitle":"India"},"title":"Chapai Nawabganj","rightDetail":"49 km"},{"page":{"map":"f09uPaXs","url":"/visit/rajshahi/f09uPaXs","type":"page","count":1,"title":"Rajshahi","subtitle":"India"},"title":"Rajshahi","rightDetail":"87 km"},{"page":{"map":"wtU7bpKo","url":"/visit/bhagalpur/wtU7bpKo","type":"page","count":2,"title":"Bhagalpur","subtitle":"India"},"title":"Bhagalpur","rightDetail":"119 km"},{"page":{"map":"MdUqp1Fl","url":"/visit/dumka/MdUqp1Fl","type":"page","count":1,"title":"Dumka","subtitle":"India"},"title":"Dumka","rightDetail":"122 km"},{"page":{"map":"sh_fnykm","url":"/visit/deoghar/sh_fnykm","type":"page","count":1,"title":"Deoghar","subtitle":"India"},"title":"Deoghar","rightDetail":"158 km"}]},{"rightAccessory":"chevron-right","title":"Cities in India","type":"list","items":[{"page":{"map":"7rvuWwf7","url":"/visit/mumbai/7rvuWwf7","type":"page","count":34,"title":"Mumbai","subtitle":"India"},"title":"Mumbai","leftAccessory":"count","leftAccessoryCount":34},{"page":{"map":"ILO7kNZM","url":"/visit/bengaluru/ILO7kNZM","type":"page","count":20,"title":"Bengaluru","subtitle":"India"},"title":"Bengaluru","leftAccessory":"count","leftAccessoryCount":20},{"page":{"map":"jKelPaRC","url":"/visit/chennai/jKelPaRC","type":"page","count":19,"title":"Chennai","subtitle":"India"},"title":"Chennai","leftAccessory":"count","leftAccessoryCount":19},{"page":{"map":"WgJbBi4M","url":"/visit/surat/WgJbBi4M","type":"page","count":6,"title":"Surat","subtitle":"India"},"title":"Surat","leftAccessory":"count","leftAccessoryCount":6},{"page":{"map":"ZUBCyUWi","url":"/visit/thiruvalla/ZUBCyUWi","type":"page","count":6,"title":"Thiruvalla","subtitle":"India"},"title":"Thiruvalla","leftAccessory":"count","leftAccessoryCount":6},{"page":{"map":"aZHAwwPE","url":"/visit/thrissur/aZHAwwPE","type":"page","count":6,"title":"Thrissur","subtitle":"India"},"title":"Thrissur","leftAccessory":"count","leftAccessoryCount":6},{"page":{"map":"28SHimVW","url":"/visit/pune/28SHimVW","type":"page","count":5,"title":"Pune","subtitle":"India"},"title":"Pune","leftAccessory":"count","leftAccessoryCount":5},{"page":{"map":"LHZkeK7d","url":"/visit/new-delhi/LHZkeK7d","type":"page","count":5,"title":"New Delhi","subtitle":"India"},"title":"New Delhi","leftAccessory":"count","leftAccessoryCount":5}]}]}}