{"apiVersion":0,"version":"6cae702","data":{"type":"page","count":1,"map":"73nwZKlX","title":"Bošnjace","subtitle":"Serbia","url":"/visit/bosnjace/73nwZKlX","utcOffset":120,"content":[{"items":[{"page":{"url":"/listen/radio-sunset/iSRSANfd","type":"channel","place":{"id":"73nwZKlX","title":"Bošnjace"},"title":"Radio Sunset","secure":true,"country":{"id":"7ecyBSAs","title":"Serbia"},"stream":"cmr-hosting.com"}}],"itemsType":"channel","title":"Stations in Bošnjace","type":"list"},{"itemsType":"channel","title":"Picks from the Area","type":"list","items":[{"page":{"url":"/listen/radio-llapi-fm-103-2/lRWKTI6U","type":"channel","place":{"id":"yvkSBGLR","title":"Podujevo"},"title":"Radio Llapi FM 103.2","secure":true,"country":{"id":"VdGL2O9V","title":"Kosovo"},"subtitle":"Podujevo","stream":"1dhe1.com"}},{"page":{"url":"/listen/radio-maria-kosove/sdWfbsQr","type":"channel","place":{"id":"Y3FpsQ04","title":"Prishtina"},"title":"Radio Maria Kosove","secure":true,"country":{"id":"VdGL2O9V","title":"Kosovo"},"subtitle":"Prishtina","stream":"dreamsiteradiocp2.com"}},{"page":{"url":"/listen/nisville-radio/3R4voqTG","type":"channel","place":{"id":"9Yxlma1M","title":"Niš"},"title":"Nisville Online Radio","secure":true,"country":{"id":"7ecyBSAs","title":"Serbia"},"subtitle":"Niš","stream":"nisville.com"}},{"page":{"url":"/listen/radio-star-96-4-fm/PRQPJSKo","type":"channel","place":{"id":"TZK2Mk2d","title":"Gjilan"},"title":"Radio Star 96.4 FM","secure":true,"country":{"id":"VdGL2O9V","title":"Kosovo"},"subtitle":"Gjilan","stream":"1dhe1.com"}}]},{"itemsType":"channel","title":"Popular in Serbia","type":"list","items":[{"page":{"url":"/listen/radio-lola/fjKyclRo","type":"channel","place":{"id":"nkeutQ57","title":"Belgrade"},"title":"Radio LOLA","secure":true,"country":{"id":"7ecyBSAs","title":"Serbia"},"subtitle":"Belgrade","stream":"tdiradio.com"}},{"page":{"url":"/listen/naxi-ex-yu-radio/e3SG81FL","type":"channel","place":{"id":"nkeutQ57","title":"Belgrade"},"title":"Naxi EX YU Radio","secure":true,"country":{"id":"7ecyBSAs","title":"Serbia"},"subtitle":"Belgrade","stream":"streaming.rs"}},{"page":{"url":"/listen/karolina/Bls5hbrq","type":"channel","place":{"id":"nkeutQ57","title":"Belgrade"},"title":"Radio Karolina","secure":true,"country":{"id":"7ecyBSAs","title":"Serbia"},"subtitle":"Belgrade","stream":"karolina.rs"}},{"page":{"url":"/listen/naxi-radio-fm/M3byJpiQ","type":"channel","place":{"id":"nkeutQ57","title":"Belgrade"},"title":"Naxi Radio FM","secure":true,"country":{"id":"7ecyBSAs","title":"Serbia"},"subtitle":"Belgrade","stream":"streaming.rs"}},{"page":{"url":"/listen/radio-s-kafana/gFjPunuF","type":"channel","place":{"id":"nkeutQ57","title":"Belgrade"},"title":"Radio S 3 Narodni","secure":true,"country":{"id":"7ecyBSAs","title":"Serbia"},"subtitle":"Belgrade","stream":"radios.rs"}},{"rightAccessory":"chevron-right","title":"Go to Serbia","type":"more","page":{"type":"page","title":"Serbia","url":"/visit/serbia/7ecyBSAs"}}]},{"rightAccessory":"chevron-right","title":"Nearby Bošnjace","type":"list","items":[{"page":{"map":"9Yxlma1M","url":"/visit/nis/9Yxlma1M","type":"page","count":4,"title":"Niš","subtitle":"Serbia"},"title":"Niš","rightDetail":"41 km"},{"page":{"map":"yvkSBGLR","url":"/visit/podujevo/yvkSBGLR","type":"page","count":1,"title":"Podujevo","subtitle":"Serbia"},"title":"Podujevo","rightDetail":"49 km"},{"page":{"map":"TZK2Mk2d","url":"/visit/gjilan/TZK2Mk2d","type":"page","count":1,"title":"Gjilan","subtitle":"Serbia"},"title":"Gjilan","rightDetail":"61 km"},{"page":{"map":"Y3FpsQ04","url":"/visit/prishtina/Y3FpsQ04","type":"page","count":14,"title":"Prishtina","subtitle":"Serbia"},"title":"Prishtina","rightDetail":"61 km"}]},{"rightAccessory":"chevron-right","title":"Cities in Serbia","type":"list","items":[{"page":{"map":"nkeutQ57","url":"/visit/belgrade/nkeutQ57","type":"page","count":94,"title":"Belgrade","subtitle":"Serbia"},"title":"Belgrade","leftAccessory":"count","leftAccessoryCount":94},{"page":{"map":"YV9iOSCg","url":"/visit/novi-sad/YV9iOSCg","type":"page","count":10,"title":"Novi Sad","subtitle":"Serbia"},"title":"Novi Sad","leftAccessory":"count","leftAccessoryCount":10},{"page":{"map":"b8UxkMAj","url":"/visit/subotica/b8UxkMAj","type":"page","count":4,"title":"Subotica","subtitle":"Serbia"},"title":"Subotica","leftAccessory":"count","leftAccessoryCount":4},{"page":{"map":"9Yxlma1M","url":"/visit/nis/9Yxlma1M","type":"page","count":4,"title":"Niš","subtitle":"Serbia"},"title":"Niš","leftAccessory":"count","leftAccessoryCount":4},{"page":{"map":"LDHwPU1A","url":"/visit/loznica/LDHwPU1A","type":"page","count":3,"title":"Loznica","subtitle":"Serbia"},"title":"Loznica","leftAccessory":"count","leftAccessoryCount":3},{"page":{"map":"xonzeqRY","url":"/visit/jagodina/xonzeqRY","type":"page","count":3,"title":"Jagodina","subtitle":"Serbia"},"title":"Jagodina","leftAccessory":"count","leftAccessoryCount":3},{"page":{"map":"5MRxDmMF","url":"/visit/kraljevo/5MRxDmMF","type":"page","count":3,"title":"Kraljevo","subtitle":"Serbia"},"title":"Kraljevo","leftAccessory":"count","leftAccessoryCount":3},{"page":{"map":"atpjZFxS","url":"/visit/uzice/atpjZFxS","type":"page","count":3,"title":"Užice","subtitle":"Serbia"},"title":"Užice","leftAccessory":"count","leftAccessoryCount":3}]}]}}