{"apiVersion":0,"version":"6cae702","data":{"type":"page","count":1,"map":"em4bPfwu","title":"Città di San Marino","subtitle":"San Marino","url":"/visit/citta-di-san-marino/em4bPfwu","utcOffset":120,"content":[{"items":[{"page":{"url":"/listen/usmaradio/A6NGSkR0","type":"channel","place":{"id":"em4bPfwu","title":"Città di San Marino"},"title":"USMARADIO","secure":true,"country":{"id":"slBbQfKq","title":"San Marino"},"stream":"airtime.pro"}}],"itemsType":"channel","title":"Stations in Città di San Marino","type":"list"},{"itemsType":"channel","title":"Picks from the Area","type":"list","items":[{"page":{"url":"/listen/radio-gamma/CAUkbaws","type":"channel","place":{"id":"aansgsn4","title":"Forlimpopoli"},"title":"Radio Gamma","secure":true,"country":{"id":"rUtTcuHL","title":"Italy"},"subtitle":"Forlimpopoli","stream":"xdevel.com"}},{"page":{"url":"/listen/radio-centrale-cesena/IUTqdmug","type":"channel","place":{"id":"L8SQC8eu","title":"Cesena"},"title":"Radio Centrale Cesena","secure":true,"country":{"id":"rUtTcuHL","title":"Italy"},"subtitle":"Cesena","stream":"fluidstream.net"}},{"page":{"url":"/listen/cosmic-fringe-radio/2u-szWI3","type":"channel","place":{"id":"BtPJFJZV","title":"Pennabilli"},"title":"Cosmic Fringe Radio","secure":true,"country":{"id":"rUtTcuHL","title":"Italy"},"subtitle":"Pennabilli","stream":"streamtheworld.com"}},{"page":{"url":"/listen/radio-octopus/-Cqsh4Xg","type":"channel","place":{"id":"uAvXtdlH","title":"Pesaro"},"title":"Radio Octopus","secure":true,"country":{"id":"rUtTcuHL","title":"Italy"},"subtitle":"Pesaro","stream":"newradio.it"}},{"page":{"url":"/listen/radiosabbia/U6d76eHu","type":"channel","place":{"id":"hWh7S1Zl","title":"Riccione"},"title":"Radio Sabbia","secure":true,"country":{"id":"rUtTcuHL","title":"Italy"},"subtitle":"Riccione","stream":"inmystream.it"}}]},{"itemsType":"channel","title":"Popular in San Marino","type":"list","items":[{"page":{"url":"/listen/usmaradio/A6NGSkR0","type":"channel","place":{"id":"em4bPfwu","title":"Città di San Marino"},"title":"USMARADIO","secure":true,"country":{"id":"slBbQfKq","title":"San Marino"},"subtitle":"Città di San Marino","stream":"airtime.pro"}}]},{"rightAccessory":"chevron-right","title":"Nearby Città di San Marino","type":"list","items":[{"page":{"map":"FGWSXBGW","url":"/visit/santarcangelo-di-romagna/FGWSXBGW","type":"page","count":1,"title":"Santarcangelo di Romagna","subtitle":"San Marino"},"title":"Santarcangelo di Romagna","rightDetail":"14 km"},{"page":{"map":"hWh7S1Zl","url":"/visit/riccione/hWh7S1Zl","type":"page","count":1,"title":"Riccione","subtitle":"San Marino"},"title":"Riccione","rightDetail":"18 km"},{"page":{"map":"D9I7QWHq","url":"/visit/rimini/D9I7QWHq","type":"page","count":4,"title":"Rimini","subtitle":"San Marino"},"title":"Rimini","rightDetail":"18 km"},{"page":{"map":"BtPJFJZV","url":"/visit/pennabilli/BtPJFJZV","type":"page","count":1,"title":"Pennabilli","subtitle":"San Marino"},"title":"Pennabilli","rightDetail":"20 km"},{"page":{"map":"aoyHMPBk","url":"/visit/misano-adriatico/aoyHMPBk","type":"page","count":1,"title":"Misano Adriatico","subtitle":"San Marino"},"title":"Misano Adriatico","rightDetail":"21 km"}]}]}}