{"apiVersion":0,"version":"6cae702","data":{"type":"page","count":1,"map":"EnsZ6y0N","title":"Prestonsburg KY","subtitle":"United States","url":"/visit/prestonsburg-ky/EnsZ6y0N","utcOffset":-240,"content":[{"items":[{"page":{"url":"/listen/cmh23/esiA4aeh","type":"channel","place":{"id":"EnsZ6y0N","title":"Prestonsburg KY"},"title":"CMH23","secure":true,"country":{"id":"GhDXw4EW","title":"United States"},"stream":"cdnstream.com"}}],"itemsType":"channel","title":"Stations in Prestonsburg KY","type":"list"},{"itemsType":"channel","title":"Picks from the Area","type":"list","items":[{"page":{"url":"/listen/wfgh-fm-90-7/W2moT4NK","type":"channel","place":{"id":"76HV0IaA","title":"Fort Gay WV"},"title":"WFGH FM 90.7","secure":true,"country":{"id":"GhDXw4EW","title":"United States"},"subtitle":"Fort Gay WV","stream":"voscast.com"}},{"page":{"url":"/listen/-93-7-the-dawg-wdgg/DtenHiUq","type":"channel","place":{"id":"i98j1QEL","title":"Huntington WV"},"title":"WDGG FM 93.7 The Dawg","secure":true,"country":{"id":"GhDXw4EW","title":"United States"},"subtitle":"Huntington WV","stream":"securenetsystems.net"}},{"page":{"url":"/listen/wlsd-fm-92-5/sMckqtMV","type":"channel","place":{"id":"RsA1xj65","title":"Norton VA"},"title":"WLSD FM 92.5","secure":true,"country":{"id":"GhDXw4EW","title":"United States"},"subtitle":"Norton VA","stream":"appalachian.net"}},{"page":{"url":"/listen/we-are-blessed-radio/keRFr1AG","type":"channel","place":{"id":"D9Mkb6MG","title":"Pikeville KY"},"title":"We are Blessed Radio","secure":true,"country":{"id":"GhDXw4EW","title":"United States"},"subtitle":"Pikeville KY","stream":"cdnstream.com"}},{"page":{"url":"/listen/wxkq-fm-103-9/nNMDox29","type":"channel","place":{"id":"kDMlR3nu","title":"Whitesburg KY"},"title":"WXKQ-FM 103.9","secure":true,"country":{"id":"GhDXw4EW","title":"United States"},"subtitle":"Whitesburg KY","stream":"streamtheworld.com"}}]},{"itemsType":"channel","title":"Popular in United States","type":"list","items":[{"page":{"url":"/listen/smooth-jazz-24-7/1vlrqH6v","type":"channel","place":{"id":"9Yi25umJ","title":"New York NY"},"title":"Smooth Jazz 24/7","secure":true,"country":{"id":"GhDXw4EW","title":"United States"},"subtitle":"New York NY","stream":"cdnstream1.com"}},{"page":{"url":"/listen/fox-news-radio/JBY4BMqo","type":"channel","place":{"id":"9Yi25umJ","title":"New York NY"},"title":"Fox News Radio","secure":true,"country":{"id":"GhDXw4EW","title":"United States"},"subtitle":"New York NY","stream":"amperwave.net"}},{"page":{"url":"/listen/abn-old-time-radio-am-1610/niBbz3BR","type":"channel","place":{"id":"w54BkVPL","title":"Antioch IL"},"title":"ABN Old-Time Radio AM 1610","secure":true,"country":{"id":"GhDXw4EW","title":"United States"},"subtitle":"Antioch IL","stream":"yesstreaming.net"}},{"page":{"url":"/listen/npr-24-hour-program-stream/LpZn0LbR","type":"channel","place":{"id":"DIlWBUQt","title":"Washington DC"},"title":"NPR 24 Hour Program Stream","secure":true,"country":{"id":"GhDXw4EW","title":"United States"},"subtitle":"Washington DC","stream":"streamguys1.com"}},{"page":{"url":"/listen/kbrw/2C53TjhO","type":"channel","place":{"id":"fmHXuKjL","title":"Barrow AK"},"title":"KBRW-AM 680","secure":true,"country":{"id":"GhDXw4EW","title":"United States"},"subtitle":"Barrow AK","stream":"streamguys1.com"}},{"rightAccessory":"chevron-right","title":"Go to United States","type":"more","page":{"type":"page","title":"United States","url":"/visit/united-states/GhDXw4EW"}}]},{"rightAccessory":"chevron-right","title":"Nearby Prestonsburg KY","type":"list","items":[{"page":{"map":"q5xlbKPl","url":"/visit/harold-ky/q5xlbKPl","type":"page","count":1,"title":"Harold KY","subtitle":"United States"},"title":"Harold KY","rightDetail":"19 km"},{"page":{"map":"D9Mkb6MG","url":"/visit/pikeville-ky/D9Mkb6MG","type":"page","count":3,"title":"Pikeville KY","subtitle":"United States"},"title":"Pikeville KY","rightDetail":"30 km"},{"page":{"map":"59mSeeEz","url":"/visit/williamson-wv/59mSeeEz","type":"page","count":1,"title":"Williamson WV","subtitle":"United States"},"title":"Williamson WV","rightDetail":"44 km"},{"page":{"map":"76HV0IaA","url":"/visit/fort-gay-wv/76HV0IaA","type":"page","count":1,"title":"Fort Gay WV","subtitle":"United States"},"title":"Fort Gay WV","rightDetail":"52 km"},{"page":{"map":"ymCQsQXO","url":"/visit/jackson-ky/ymCQsQXO","type":"page","count":1,"title":"Jackson KY","subtitle":"United States"},"title":"Jackson KY","rightDetail":"55 km"}]},{"rightAccessory":"chevron-right","title":"Cities in United States","type":"list","items":[{"page":{"map":"9Yi25umJ","url":"/visit/new-york-ny/9Yi25umJ","type":"page","count":167,"title":"New York NY","subtitle":"United States"},"title":"New York NY","leftAccessory":"count","leftAccessoryCount":167},{"page":{"map":"LbmJqSyY","url":"/visit/san-francisco-ca/LbmJqSyY","type":"page","count":84,"title":"San Francisco CA","subtitle":"United States"},"title":"San Francisco CA","leftAccessory":"count","leftAccessoryCount":84},{"page":{"map":"qRhxzkLk","url":"/visit/los-angeles-ca/qRhxzkLk","type":"page","count":75,"title":"Los Angeles CA","subtitle":"United States"},"title":"Los Angeles CA","leftAccessory":"count","leftAccessoryCount":75},{"page":{"map":"D1wk1w5c","url":"/visit/chicago-il/D1wk1w5c","type":"page","count":70,"title":"Chicago IL","subtitle":"United States"},"title":"Chicago IL","leftAccessory":"count","leftAccessoryCount":70},{"page":{"map":"3bOmI9Vi","url":"/visit/miami-fl/3bOmI9Vi","type":"page","count":64,"title":"Miami FL","subtitle":"United States"},"title":"Miami FL","leftAccessory":"count","leftAccessoryCount":64},{"page":{"map":"ImZ4Qzhn","url":"/visit/atlanta-ga/ImZ4Qzhn","type":"page","count":48,"title":"Atlanta GA","subtitle":"United States"},"title":"Atlanta GA","leftAccessory":"count","leftAccessoryCount":48},{"page":{"map":"PPM2Rql0","url":"/visit/seattle-wa/PPM2Rql0","type":"page","count":42,"title":"Seattle WA","subtitle":"United States"},"title":"Seattle WA","leftAccessory":"count","leftAccessoryCount":42},{"page":{"map":"KnYDdnLA","url":"/visit/salt-lake-city-ut/KnYDdnLA","type":"page","count":38,"title":"Salt Lake City UT","subtitle":"United States"},"title":"Salt Lake City UT","leftAccessory":"count","leftAccessoryCount":38}]}]}}