{"apiVersion":0,"version":"6cae702","data":{"type":"page","count":2,"map":"et08Fj1m","title":"Baza","subtitle":"Spain","url":"/visit/baza/et08Fj1m","utcOffset":120,"content":[{"items":[{"page":{"url":"/listen/la-fresca-baza-88-9-fm/nJZoiwrV","type":"channel","place":{"id":"et08Fj1m","title":"Baza"},"title":"La Fresca Baza 88.9 FM","secure":true,"country":{"id":"V9cvEXA9","title":"Spain"},"stream":"produccionesdale.com"}},{"page":{"url":"/listen/radio-baza-ser/YIimG9Y8","type":"channel","place":{"id":"et08Fj1m","title":"Baza"},"title":"Radio Baza - Ser","secure":true,"country":{"id":"V9cvEXA9","title":"Spain"},"stream":"streamtheworld.com"}}],"itemsType":"channel","title":"Stations in Baza","type":"list"},{"itemsType":"channel","title":"Picks from the Area","type":"list","items":[{"page":{"url":"/listen/la-fresca-guadix-90-4fm/pypV5GQE","type":"channel","place":{"id":"yoZ5ddVq","title":"Guadix"},"title":"laFRESCA Guadix 90.4 FM","secure":true,"country":{"id":"V9cvEXA9","title":"Spain"},"subtitle":"Guadix","stream":"produccionesdale.com"}},{"page":{"url":"/listen/almeria-gold-95-5/OpAvSilN","type":"channel","place":{"id":"jVnBVbX9","title":"Albox"},"title":"Almeria Gold 95.5","secure":true,"country":{"id":"V9cvEXA9","title":"Spain"},"subtitle":"Albox","stream":"almeriaradio.live"}},{"page":{"url":"/listen/m80-radio-andalucia-este/pPwmEPZ3","type":"channel","place":{"id":"OFiKLyNr","title":"Huéscar"},"title":"M80 Radio Andalucia Este","secure":true,"country":{"id":"V9cvEXA9","title":"Spain"},"subtitle":"Huéscar","stream":"streamtheworld.com"}},{"page":{"url":"/listen/radio-berja-107-6-fm/sIpkAO17","type":"channel","place":{"id":"RkVReJeq","title":"Berja"},"title":"Radio Berja 107.6 FM","secure":true,"country":{"id":"V9cvEXA9","title":"Spain"},"subtitle":"Berja","stream":"radioponiente.org"}},{"page":{"url":"/listen/radio-cullar-fm/G1tpbEPZ","type":"channel","place":{"id":"JqkvXa43","title":"Cúllar"},"title":"Radio Cullar FM 107.8","secure":true,"country":{"id":"V9cvEXA9","title":"Spain"},"subtitle":"Cúllar","stream":"elitecomunicacion.es"}}]},{"itemsType":"channel","title":"Popular in Spain","type":"list","items":[{"page":{"url":"/listen/cope-madrid/RO3xvxeU","type":"channel","place":{"id":"hFG1a7Dk","title":"Madrid"},"title":"COPE Madrid","secure":true,"country":{"id":"V9cvEXA9","title":"Spain"},"subtitle":"Madrid","stream":"flumotion.com"}},{"page":{"url":"/listen/cadenaser/piGwX76D","type":"channel","place":{"id":"hFG1a7Dk","title":"Madrid"},"title":"Cadena Ser","secure":true,"country":{"id":"V9cvEXA9","title":"Spain"},"subtitle":"Madrid","stream":"streamtheworld.com"}},{"page":{"url":"/listen/esradio/HGMbdCXa","type":"channel","place":{"id":"hFG1a7Dk","title":"Madrid"},"title":"esRadio","secure":true,"country":{"id":"V9cvEXA9","title":"Spain"},"subtitle":"Madrid","stream":"flumotion.com"}},{"page":{"url":"/listen/rock-fm/rjv2cBe2","type":"channel","place":{"id":"hFG1a7Dk","title":"Madrid"},"title":"Rock FM","secure":true,"country":{"id":"V9cvEXA9","title":"Spain"},"subtitle":"Madrid","stream":"flumotion.com"}},{"page":{"url":"/listen/cadena-100/D1UBtS5T","type":"channel","place":{"id":"hFG1a7Dk","title":"Madrid"},"title":"Cadena 100","secure":true,"country":{"id":"V9cvEXA9","title":"Spain"},"subtitle":"Madrid","stream":"flumotion.com"}},{"rightAccessory":"chevron-right","title":"Go to Spain","type":"more","page":{"type":"page","title":"Spain","url":"/visit/spain/V9cvEXA9"}}]},{"rightAccessory":"chevron-right","title":"Nearby Baza","type":"list","items":[{"page":{"map":"JqkvXa43","url":"/visit/cullar/JqkvXa43","type":"page","count":1,"title":"Cúllar","subtitle":"Spain"},"title":"Cúllar","rightDetail":"21 km"},{"page":{"map":"LciPA37w","url":"/visit/galera/LciPA37w","type":"page","count":1,"title":"Galera","subtitle":"Spain"},"title":"Galera","rightDetail":"35 km"},{"page":{"map":"yoZ5ddVq","url":"/visit/guadix/yoZ5ddVq","type":"page","count":5,"title":"Guadix","subtitle":"Spain"},"title":"Guadix","rightDetail":"38 km"},{"page":{"map":"OFiKLyNr","url":"/visit/huescar/OFiKLyNr","type":"page","count":1,"title":"Huéscar","subtitle":"Spain"},"title":"Huéscar","rightDetail":"41 km"},{"page":{"map":"JtXZJR88","url":"/visit/fines/JtXZJR88","type":"page","count":1,"title":"Fines","subtitle":"Spain"},"title":"Fines","rightDetail":"47 km"}]},{"rightAccessory":"chevron-right","title":"Cities in Spain","type":"list","items":[{"page":{"map":"hFG1a7Dk","url":"/visit/madrid/hFG1a7Dk","type":"page","count":104,"title":"Madrid","subtitle":"Spain"},"title":"Madrid","leftAccessory":"count","leftAccessoryCount":104},{"page":{"map":"DySRBHdL","url":"/visit/barcelona/DySRBHdL","type":"page","count":44,"title":"Barcelona","subtitle":"Spain"},"title":"Barcelona","leftAccessory":"count","leftAccessoryCount":44},{"page":{"map":"BQp7EEgW","url":"/visit/palma/BQp7EEgW","type":"page","count":35,"title":"Palma de Mallorca","subtitle":"Spain"},"title":"Palma de Mallorca","leftAccessory":"count","leftAccessoryCount":35},{"page":{"map":"xdFoGP7o","url":"/visit/malaga/xdFoGP7o","type":"page","count":33,"title":"Málaga","subtitle":"Spain"},"title":"Málaga","leftAccessory":"count","leftAccessoryCount":33},{"page":{"map":"yww6IvMD","url":"/visit/valencia/yww6IvMD","type":"page","count":25,"title":"Valencia","subtitle":"Spain"},"title":"Valencia","leftAccessory":"count","leftAccessoryCount":25},{"page":{"map":"6DT6YRBu","url":"/visit/seville/6DT6YRBu","type":"page","count":24,"title":"Seville","subtitle":"Spain"},"title":"Seville","leftAccessory":"count","leftAccessoryCount":24},{"page":{"map":"UpWDKzmZ","url":"/visit/ibiza/UpWDKzmZ","type":"page","count":22,"title":"Ibiza","subtitle":"Spain"},"title":"Ibiza","leftAccessory":"count","leftAccessoryCount":22},{"page":{"map":"BAybPmHT","url":"/visit/santa-cruz-de-tenerife/BAybPmHT","type":"page","count":21,"title":"Santa Cruz de Tenerife","subtitle":"Spain"},"title":"Santa Cruz de Tenerife","leftAccessory":"count","leftAccessoryCount":21}]}]}}