{"apiVersion":0,"version":"6cae702","data":{"type":"page","count":1,"map":"kYO9aAKA","title":"Manama","subtitle":"Bahrain","url":"/visit/manama/kYO9aAKA","utcOffset":180,"content":[{"items":[{"page":{"url":"/listen/radio-bahrain-96-5-fm/KDWcskj5","type":"channel","place":{"id":"kYO9aAKA","title":"Manama"},"title":"Radio Bahrain 96.5 FM","secure":true,"country":{"id":"jtyBoKzI","title":"Bahrain"},"stream":"aiir.com"}}],"itemsType":"channel","title":"Stations in Manama","type":"list"},{"itemsType":"channel","title":"Picks from the Area","type":"list","items":[{"page":{"url":"/listen/annahj/b0pxB-rA","type":"channel","place":{"id":"K1zI2Bsg","title":"Kuwait City"},"title":"Alnahj","secure":true,"country":{"id":"DOy7fR6r","title":"Kuwait"},"subtitle":"Kuwait City","stream":"obviousapproach.com"}},{"page":{"url":"/listen/radio-olive-kids/stIiMoBP","type":"channel","place":{"id":"8rD5mXZo","title":"Doha"},"title":"Radio Olive Kids","secure":true,"country":{"id":"MA1NhUt1","title":"Qatar"},"subtitle":"Doha","stream":"streamtheworld.com"}},{"page":{"url":"/listen/radio-asharq-with-bloomberg/ML1QwVJk","type":"channel","place":{"id":"8LXuEJLc","title":"Riyadh"},"title":"Radio Asharq with Bloomberg","secure":true,"country":{"id":"JRDaNdLK","title":"Saudi Arabia"},"subtitle":"Riyadh","stream":"itworkscdn.net"}},{"page":{"url":"/listen/pravasi-bharathi-810-am/yaBB7hCL","type":"channel","place":{"id":"udYmSMsn","title":"Abu Dhabi"},"title":"Pravasi Bharathi 810 AM","secure":true,"country":{"id":"7lP6QwLE","title":"United Arab Emirates"},"subtitle":"Abu Dhabi","stream":"pravasibharathiradio.com"}},{"page":{"url":"/listen/radio-4-fm-89-1/GUUFY9TW","type":"channel","place":{"id":"7Oa7oR3O","title":"Ajman"},"title":"Radio 4 FM 89.1","secure":true,"country":{"id":"7lP6QwLE","title":"United Arab Emirates"},"subtitle":"Ajman","stream":"radio.co"}}]},{"itemsType":"channel","title":"Popular in Bahrain","type":"list","items":[{"page":{"url":"/listen/radio-bahrain-96-5-fm/KDWcskj5","type":"channel","place":{"id":"kYO9aAKA","title":"Manama"},"title":"Radio Bahrain 96.5 FM","secure":true,"country":{"id":"jtyBoKzI","title":"Bahrain"},"subtitle":"Manama","stream":"aiir.com"}}]},{"rightAccessory":"chevron-right","title":"Nearby Manama","type":"list","items":[{"page":{"map":"IFwQAuAq","url":"/visit/lusail/IFwQAuAq","type":"page","count":1,"title":"Lusail","subtitle":"Bahrain"},"title":"Lusail","rightDetail":"128 km"},{"page":{"map":"8rD5mXZo","url":"/visit/doha/8rD5mXZo","type":"page","count":16,"title":"Doha","subtitle":"Bahrain"},"title":"Doha","rightDetail":"141 km"},{"page":{"map":"5UKnhPrk","url":"/visit/al-wakrah/5UKnhPrk","type":"page","count":1,"title":"Al Wakrah","subtitle":"Bahrain"},"title":"Al Wakrah","rightDetail":"156 km"},{"page":{"map":"8LXuEJLc","url":"/visit/riyadh/8LXuEJLc","type":"page","count":3,"title":"Riyadh","subtitle":"Bahrain"},"title":"Riyadh","rightDetail":"428 km"},{"page":{"map":"udYmSMsn","url":"/visit/abu-dhabi/udYmSMsn","type":"page","count":2,"title":"Abu Dhabi","subtitle":"Bahrain"},"title":"Abu Dhabi","rightDetail":"432 km"}]}]}}