{"apiVersion":0,"version":"6cae702","data":{"type":"page","count":1,"map":"llcaxy6C","title":"Rosário do Sul RS","subtitle":"Brazil","url":"/visit/rosario-do-sul-rs/llcaxy6C","utcOffset":-180,"content":[{"items":[{"page":{"url":"/listen/radio-maraja-am-660/6cxonTw0","type":"channel","place":{"id":"llcaxy6C","title":"Rosário do Sul RS"},"title":"Rádio Marajá AM 660","secure":true,"country":{"id":"Fx52MfoZ","title":"Brazil"},"stream":"brlogic.com"}}],"itemsType":"channel","title":"Stations in Rosário do Sul RS","type":"list"},{"itemsType":"channel","title":"Picks from the Area","type":"list","items":[{"page":{"url":"/listen/minuano-fm-97-5/eLktGP3j","type":"channel","place":{"id":"blngPs7s","title":"Alegrete RS"},"title":"Minuano FM 97.5","secure":true,"country":{"id":"Fx52MfoZ","title":"Brazil"},"subtitle":"Alegrete RS","stream":"i9suaradio.com"}},{"page":{"url":"/listen/radio-upacarai/qiqTRNCZ","type":"channel","place":{"id":"KTdQ7G2a","title":"Dom Pedrito RS"},"title":"Rádio Upacaraí AM 1330","secure":true,"country":{"id":"Fx52MfoZ","title":"Brazil"},"subtitle":"Dom Pedrito RS","stream":"com.br"}},{"page":{"url":"/listen/radio-jaguari-fm-100-1/U3kl8pSZ","type":"channel","place":{"id":"gK2GKvTX","title":"Jaguari RS"},"title":"Radio Jaguari FM 100.1","secure":true,"country":{"id":"Fx52MfoZ","title":"Brazil"},"subtitle":"Jaguari RS","stream":"ciclano.io"}},{"page":{"url":"/listen/radio-batista-livramento/WH3vKl4l","type":"channel","place":{"id":"nwAKF3hz","title":"Santana do Livramento RS"},"title":"Rádio Batista Livramento","secure":true,"country":{"id":"Fx52MfoZ","title":"Brazil"},"subtitle":"Santana do Livramento RS","stream":"com.br"}},{"page":{"url":"/listen/radio-nova-pauta-fm-100-7/2ecVA6uf","type":"channel","place":{"id":"KICQnDd3","title":"Santiago RS"},"title":"Radio Nova Pauta FM 100.7","secure":true,"country":{"id":"Fx52MfoZ","title":"Brazil"},"subtitle":"Santiago RS","stream":"com.br"}}]},{"itemsType":"channel","title":"Popular in Brazil","type":"list","items":[{"page":{"url":"/listen/antena1/Q6JROd6G","type":"channel","place":{"id":"BMplqTGe","title":"São Paulo SP"},"title":"Antena 1 FM 94.7","secure":true,"country":{"id":"Fx52MfoZ","title":"Brazil"},"subtitle":"São Paulo SP","stream":"com.br"}},{"page":{"url":"/listen/radio-itatiaia-am-610/6eva9Gaq","type":"channel","place":{"id":"eCT4ymBs","title":"Belo Horizonte MG"},"title":"Rádio Itatiaia","secure":true,"country":{"id":"Fx52MfoZ","title":"Brazil"},"subtitle":"Belo Horizonte MG","stream":"com.br"}},{"page":{"url":"/listen/alpha-fm-101-7-mhz/PUSmt3pf","type":"channel","place":{"id":"BMplqTGe","title":"São Paulo SP"},"title":"Alpha FM 101.7","secure":true,"country":{"id":"Fx52MfoZ","title":"Brazil"},"subtitle":"São Paulo SP","stream":"streamtheworld.com"}},{"page":{"url":"/listen/antena-1/dc1sNhdr","type":"channel","place":{"id":"FlL4ab42","title":"Florianópolis SC"},"title":"Antena 1","secure":true,"country":{"id":"Fx52MfoZ","title":"Brazil"},"subtitle":"Florianópolis SC","stream":"com.br"}},{"page":{"url":"/listen/radio-jb-fm-99-9/2IS4841d","type":"channel","place":{"id":"zBzV2plE","title":"Rio de Janeiro RJ"},"title":"Rádio JB FM 99,9","secure":true,"country":{"id":"Fx52MfoZ","title":"Brazil"},"subtitle":"Rio de Janeiro RJ","stream":"streamtheworld.com"}},{"rightAccessory":"chevron-right","title":"Go to Brazil","type":"more","page":{"type":"page","title":"Brazil","url":"/visit/brazil/Fx52MfoZ"}}]},{"rightAccessory":"chevron-right","title":"Nearby Rosário do Sul RS","type":"list","items":[{"page":{"map":"uNquSP3H","url":"/visit/sao-gabriel-rs/uNquSP3H","type":"page","count":1,"title":"São Gabriel RS","subtitle":"Brazil"},"title":"São Gabriel RS","rightDetail":"58 km"},{"page":{"map":"eFU4o7jr","url":"/visit/sao-vicente-do-sul-rs/eFU4o7jr","type":"page","count":1,"title":"São Vicente do Sul RS","subtitle":"Brazil"},"title":"São Vicente do Sul RS","rightDetail":"66 km"},{"page":{"map":"rLLJ0AeX","url":"/visit/sao-francisco-de-assis-rs/rLLJ0AeX","type":"page","count":1,"title":"São Francisco de Assis RS","subtitle":"Brazil"},"title":"São Francisco de Assis RS","rightDetail":"79 km"},{"page":{"map":"KTdQ7G2a","url":"/visit/dom-pedrito-rs/KTdQ7G2a","type":"page","count":1,"title":"Dom Pedrito RS","subtitle":"Brazil"},"title":"Dom Pedrito RS","rightDetail":"84 km"},{"page":{"map":"gK2GKvTX","url":"/visit/jaguari-rs/gK2GKvTX","type":"page","count":1,"title":"Jaguari RS","subtitle":"Brazil"},"title":"Jaguari RS","rightDetail":"87 km"}]},{"rightAccessory":"chevron-right","title":"Cities in Brazil","type":"list","items":[{"page":{"map":"BMplqTGe","url":"/visit/sao-paulo-sp/BMplqTGe","type":"page","count":149,"title":"São Paulo SP","subtitle":"Brazil"},"title":"São Paulo SP","leftAccessory":"count","leftAccessoryCount":149},{"page":{"map":"zBzV2plE","url":"/visit/rio-de-janeiro-rj/zBzV2plE","type":"page","count":77,"title":"Rio de Janeiro RJ","subtitle":"Brazil"},"title":"Rio de Janeiro RJ","leftAccessory":"count","leftAccessoryCount":77},{"page":{"map":"Dl7h95vw","url":"/visit/goiania-go/Dl7h95vw","type":"page","count":57,"title":"Goiânia GO","subtitle":"Brazil"},"title":"Goiânia GO","leftAccessory":"count","leftAccessoryCount":57},{"page":{"map":"XeRTyfXj","url":"/visit/salvador-ba/XeRTyfXj","type":"page","count":41,"title":"Salvador BA","subtitle":"Brazil"},"title":"Salvador BA","leftAccessory":"count","leftAccessoryCount":41},{"page":{"map":"rUm92TN1","url":"/visit/curitiba-pr/rUm92TN1","type":"page","count":41,"title":"Curitiba PR","subtitle":"Brazil"},"title":"Curitiba PR","leftAccessory":"count","leftAccessoryCount":41},{"page":{"map":"JA4qa8gk","url":"/visit/brasilia-df/JA4qa8gk","type":"page","count":38,"title":"Brasília DF","subtitle":"Brazil"},"title":"Brasília DF","leftAccessory":"count","leftAccessoryCount":38},{"page":{"map":"cBuAeAW4","url":"/visit/porto-alegre-rs/cBuAeAW4","type":"page","count":36,"title":"Porto Alegre RS","subtitle":"Brazil"},"title":"Porto Alegre RS","leftAccessory":"count","leftAccessoryCount":36},{"page":{"map":"eCT4ymBs","url":"/visit/belo-horizonte-mg/eCT4ymBs","type":"page","count":35,"title":"Belo Horizonte MG","subtitle":"Brazil"},"title":"Belo Horizonte MG","leftAccessory":"count","leftAccessoryCount":35}]}]}}