{"apiVersion":0,"version":"6cae702","data":{"type":"page","count":77,"map":"zBzV2plE","title":"Rio de Janeiro RJ","subtitle":"Brazil","url":"/visit/rio-de-janeiro-rj/zBzV2plE","utcOffset":-180,"content":[{"itemsType":"channel","title":"Stations in Rio de Janeiro RJ","type":"list","items":[{"page":{"url":"/listen/amil-paradiso-95-7-fm/XqJKdi5L","type":"channel","place":{"id":"zBzV2plE","title":"Rio de Janeiro RJ"},"title":"Amil Paradiso 95.7 FM","secure":true,"country":{"id":"Fx52MfoZ","title":"Brazil"},"stream":"streamtheworld.com"}},{"page":{"url":"/listen/game-fm/rxkK47U2","type":"channel","place":{"id":"zBzV2plE","title":"Rio de Janeiro RJ"},"title":"GameFM","secure":true,"country":{"id":"Fx52MfoZ","title":"Brazil"},"stream":"instainternet.com"}},{"page":{"url":"/listen/parada-mpb/cGss3GdR","type":"channel","place":{"id":"zBzV2plE","title":"Rio de Janeiro RJ"},"title":"Parada MPB","secure":true,"country":{"id":"Fx52MfoZ","title":"Brazil"},"stream":"ipstm.net"}},{"page":{"url":"/listen/radio-duzape/SIeG9qoW","type":"channel","place":{"id":"zBzV2plE","title":"Rio de Janeiro RJ"},"title":"Radio Duzape","secure":true,"country":{"id":"Fx52MfoZ","title":"Brazil"},"stream":"com.br"}},{"page":{"url":"/listen/radio-missoes/imVzuZ9O","type":"channel","place":{"id":"zBzV2plE","title":"Rio de Janeiro RJ"},"title":"Radio Missões","secure":true,"country":{"id":"Fx52MfoZ","title":"Brazil"},"stream":"brlogic.com"}},{"page":{"url":"/listen/light-fm/NKGB-Cct","type":"channel","place":{"id":"zBzV2plE","title":"Rio de Janeiro RJ"},"title":"Supernova FM","secure":true,"country":{"id":"Fx52MfoZ","title":"Brazil"},"stream":"com.br"}},{"page":{"type":"page","count":77,"map":"zBzV2plE","subtitle":"All Stations","title":"Rio de Janeiro RJ","url":"/visit/rio-de-janeiro-rj/zBzV2plE/channels"},"rightAccessory":"chevron-right","title":"View all 77 stations","type":"more"}]},{"actionPage":{"type":"page","count":77,"map":"zBzV2plE","subtitle":"Popular Stations","title":"Rio de Janeiro RJ","url":"/visit/rio-de-janeiro-rj/zBzV2plE/popular"},"actionText":"See all","items":[{"page":{"url":"/listen/radio-jb-fm-99-9/2IS4841d","type":"channel","place":{"id":"zBzV2plE","title":"Rio de Janeiro RJ"},"title":"Rádio JB FM 99,9","secure":true,"country":{"id":"Fx52MfoZ","title":"Brazil"},"stream":"streamtheworld.com"}},{"page":{"url":"/listen/super-radio-tupi-fm-96-5/RMuzTKOn","type":"channel","place":{"id":"zBzV2plE","title":"Rio de Janeiro RJ"},"title":"Super Rádio Tupi FM 96.5","secure":true,"country":{"id":"Fx52MfoZ","title":"Brazil"},"stream":"com.br"}},{"page":{"url":"/listen/radio-globo-98-1-fm/D00jZlYK","type":"channel","place":{"id":"zBzV2plE","title":"Rio de Janeiro RJ"},"title":"Radio Globo 98.1 FM","secure":true,"country":{"id":"Fx52MfoZ","title":"Brazil"},"stream":"streamtheworld.com"}},{"page":{"url":"/listen/fm-o-dia-100-5/YJX-1rfR","type":"channel","place":{"id":"zBzV2plE","title":"Rio de Janeiro RJ"},"title":"FM o Dia 100.5","secure":true,"country":{"id":"Fx52MfoZ","title":"Brazil"},"stream":"livespanel.com"}},{"page":{"url":"/listen/antena-1-rio-fm-103-7/rwYHKZfu","type":"channel","place":{"id":"zBzV2plE","title":"Rio de Janeiro RJ"},"title":"Antena 1 Rio FM 103.7","secure":true,"country":{"id":"Fx52MfoZ","title":"Brazil"},"stream":"com.br"}},{"page":{"url":"/listen/positividade-fm/I2PtGKW5","type":"channel","place":{"id":"zBzV2plE","title":"Rio de Janeiro RJ"},"title":"Positividade FM","secure":true,"country":{"id":"Fx52MfoZ","title":"Brazil"},"stream":"streamtheworld.com"}}],"itemsType":"channel","title":"Popular in Rio de Janeiro RJ","type":"list"},{"itemsType":"channel","title":"Picks from the Area","type":"list","items":[{"page":{"url":"/listen/total-remix/KX_puTlb","type":"channel","place":{"id":"aoJqjqmP","title":"Belford Roxo RJ"},"title":"Total Remix","secure":true,"country":{"id":"Fx52MfoZ","title":"Brazil"},"subtitle":"Belford Roxo RJ","stream":"oficialserver.com"}},{"page":{"url":"/listen/rvi-fm-98-7/MClkZ0A9","type":"channel","place":{"id":"R7enEAtA","title":"Duque de Caxias RJ"},"title":"RVI FM 98.7","secure":true,"country":{"id":"Fx52MfoZ","title":"Brazil"},"subtitle":"Duque de Caxias RJ","stream":"srvstm.com"}},{"page":{"url":"/listen/viagem-do-rock/5qPbJSW5","type":"channel","place":{"id":"KZ0TaR9b","title":"Maricá RJ"},"title":"Viagem do Rock","secure":true,"country":{"id":"Fx52MfoZ","title":"Brazil"},"subtitle":"Maricá RJ","stream":"brlogic.com"}},{"page":{"url":"/listen/radio-pinheiral-rock/qQgBMLCO","type":"channel","place":{"id":"kqna292k","title":"Mesquita RJ"},"title":"Rádio Pinheiral Rock","secure":true,"country":{"id":"Fx52MfoZ","title":"Brazil"},"subtitle":"Mesquita RJ","stream":"cmaudioevideo.com"}},{"page":{"url":"/listen/radio-jovem-mix/XYvdhr6k","type":"channel","place":{"id":"HBL2baI_","title":"Nilópolis RJ"},"title":"Rádio Jovem Mix","secure":true,"country":{"id":"Fx52MfoZ","title":"Brazil"},"subtitle":"Nilópolis RJ","stream":"zeno.fm"}}]},{"itemsType":"channel","title":"Popular in Brazil","type":"list","items":[{"page":{"url":"/listen/antena1/Q6JROd6G","type":"channel","place":{"id":"BMplqTGe","title":"São Paulo SP"},"title":"Antena 1 FM 94.7","secure":true,"country":{"id":"Fx52MfoZ","title":"Brazil"},"subtitle":"São Paulo SP","stream":"com.br"}},{"page":{"url":"/listen/radio-itatiaia-am-610/6eva9Gaq","type":"channel","place":{"id":"eCT4ymBs","title":"Belo Horizonte MG"},"title":"Rádio Itatiaia","secure":true,"country":{"id":"Fx52MfoZ","title":"Brazil"},"subtitle":"Belo Horizonte MG","stream":"com.br"}},{"page":{"url":"/listen/alpha-fm-101-7-mhz/PUSmt3pf","type":"channel","place":{"id":"BMplqTGe","title":"São Paulo SP"},"title":"Alpha FM 101.7","secure":true,"country":{"id":"Fx52MfoZ","title":"Brazil"},"subtitle":"São Paulo SP","stream":"streamtheworld.com"}},{"page":{"url":"/listen/antena-1/dc1sNhdr","type":"channel","place":{"id":"FlL4ab42","title":"Florianópolis SC"},"title":"Antena 1","secure":true,"country":{"id":"Fx52MfoZ","title":"Brazil"},"subtitle":"Florianópolis SC","stream":"com.br"}},{"page":{"url":"/listen/radio-jb-fm-99-9/2IS4841d","type":"channel","place":{"id":"zBzV2plE","title":"Rio de Janeiro RJ"},"title":"Rádio JB FM 99,9","secure":true,"country":{"id":"Fx52MfoZ","title":"Brazil"},"subtitle":"Rio de Janeiro RJ","stream":"streamtheworld.com"}},{"rightAccessory":"chevron-right","title":"Go to Brazil","type":"more","page":{"type":"page","title":"Brazil","url":"/visit/brazil/Fx52MfoZ"}}]},{"rightAccessory":"chevron-right","title":"Nearby Rio de Janeiro RJ","type":"list","items":[{"page":{"map":"NbhRjP6p","url":"/visit/niteroi-rj/NbhRjP6p","type":"page","count":8,"title":"Niterói RJ","subtitle":"Brazil"},"title":"Niterói RJ","rightDetail":"6 km"},{"page":{"map":"72U9wtaG","url":"/visit/sao-goncalo-rj/72U9wtaG","type":"page","count":4,"title":"São Gonçalo RJ","subtitle":"Brazil"},"title":"São Gonçalo RJ","rightDetail":"14 km"},{"page":{"map":"R7enEAtA","url":"/visit/duque-de-caxias-rj/R7enEAtA","type":"page","count":3,"title":"Duque de Caxias RJ","subtitle":"Brazil"},"title":"Duque de Caxias RJ","rightDetail":"19 km"},{"page":{"map":"HBL2baI_","url":"/visit/nilopolis-rj/HBL2baI_","type":"page","count":2,"title":"Nilópolis RJ","subtitle":"Brazil"},"title":"Nilópolis RJ","rightDetail":"27 km"},{"page":{"map":"aoJqjqmP","url":"/visit/belford-roxo-rj/aoJqjqmP","type":"page","count":1,"title":"Belford Roxo RJ","subtitle":"Brazil"},"title":"Belford Roxo RJ","rightDetail":"28 km"}]},{"rightAccessory":"chevron-right","title":"Cities in Brazil","type":"list","items":[{"page":{"map":"BMplqTGe","url":"/visit/sao-paulo-sp/BMplqTGe","type":"page","count":149,"title":"São Paulo SP","subtitle":"Brazil"},"title":"São Paulo SP","leftAccessory":"count","leftAccessoryCount":149},{"page":{"map":"Dl7h95vw","url":"/visit/goiania-go/Dl7h95vw","type":"page","count":57,"title":"Goiânia GO","subtitle":"Brazil"},"title":"Goiânia GO","leftAccessory":"count","leftAccessoryCount":57},{"page":{"map":"XeRTyfXj","url":"/visit/salvador-ba/XeRTyfXj","type":"page","count":41,"title":"Salvador BA","subtitle":"Brazil"},"title":"Salvador BA","leftAccessory":"count","leftAccessoryCount":41},{"page":{"map":"rUm92TN1","url":"/visit/curitiba-pr/rUm92TN1","type":"page","count":41,"title":"Curitiba PR","subtitle":"Brazil"},"title":"Curitiba PR","leftAccessory":"count","leftAccessoryCount":41},{"page":{"map":"JA4qa8gk","url":"/visit/brasilia-df/JA4qa8gk","type":"page","count":38,"title":"Brasília DF","subtitle":"Brazil"},"title":"Brasília DF","leftAccessory":"count","leftAccessoryCount":38},{"page":{"map":"cBuAeAW4","url":"/visit/porto-alegre-rs/cBuAeAW4","type":"page","count":36,"title":"Porto Alegre RS","subtitle":"Brazil"},"title":"Porto Alegre RS","leftAccessory":"count","leftAccessoryCount":36},{"page":{"map":"eCT4ymBs","url":"/visit/belo-horizonte-mg/eCT4ymBs","type":"page","count":35,"title":"Belo Horizonte MG","subtitle":"Brazil"},"title":"Belo Horizonte MG","leftAccessory":"count","leftAccessoryCount":35},{"page":{"map":"8auDzHOD","url":"/visit/fortaleza-ce/8auDzHOD","type":"page","count":34,"title":"Fortaleza CE","subtitle":"Brazil"},"title":"Fortaleza CE","leftAccessory":"count","leftAccessoryCount":34}]}]}}